{
  "(Miya ki) Todi": {
    "aaroha": [
      "S", 
      "r", 
      "g", 
      "M", 
      "d", 
      "N", 
      "S'"
    ], 
    "avaroha": [
      "S'", 
      "N", 
      "d", 
      "P", 
      "M", 
      "g", 
      "r", 
      "s"
    ], 
    "jati": "Sampurna-Shadav", 
    "pakad": [
      "g", 
      "M", 
      "d", 
      "M", 
      "d", 
      "N", 
      "d", 
      "N", 
      "d", 
      "P", 
      "M", 
      "d", 
      "M", 
      "g", 
      "r", 
      "g", 
      "r", 
      "g", 
      "r", 
      "S"
    ], 
    "samvadi": "g", 
    "thaat": "Todi", 
    "time": "Late Morning, 9-12", 
    "vadi": "d"
  }, 
  "Aarabhi": {
    "aaroha": [
      "S", 
      "R", 
      "m", 
      "P", 
      "D", 
      "S'"
    ], 
    "avaroha": [
      "S'", 
      "N", 
      "D", 
      "P", 
      "m", 
      "G", 
      "R", 
      "S"
    ], 
    "jati": "Audav-Sampurna", 
    "pakad": [
      "'D", 
      "S", 
      "R", 
      "m", 
      "G", 
      "R", 
      "S", 
      "'N", 
      "'D", 
      "S"
    ], 
    "samvadi": "m", 
    "thaat": "Bilaval", 
    "time": "Night, 9-12", 
    "vadi": "S"
  }, 
  "Abhogi": {
    "aaroha": [
      "S", 
      "R", 
      "g", 
      "m", 
      "D", 
      "S'"
    ], 
    "avaroha": [
      "S'", 
      "D", 
      "m", 
      "g", 
      "R", 
      "S"
    ], 
    "jati": "Audav-Audav", 
    "pakad": [
      "'D", 
      "S", 
      "R", 
      "g", 
      "m", 
      "R", 
      "g", 
      "m", 
      "R", 
      "S"
    ], 
    "samvadi": "S", 
    "thaat": "Kafi", 
    "time": "Early Night, 9-12", 
    "vadi": "m"
  }, 
  "Adana": {
    "aaroha": [
      "S", 
      "R", 
      "g", 
      "M", 
      "P", 
      "n", 
      "P", 
      "S'"
    ], 
    "avaroha": [
      "S'", 
      "d", 
      "n", 
      "P", 
      "g", 
      "M", 
      "R", 
      "s"
    ], 
    "jati": "Audav-Sampurna", 
    "pakad": [
      "S", 
      "d", 
      "n", 
      "S'", 
      "d", 
      "n", 
      "P", 
      "M", 
      "P", 
      "g", 
      "M", 
      "R", 
      "s"
    ], 
    "samvadi": "P", 
    "thaat": "Asavari", 
    "time": "Late Night, 12-3", 
    "vadi": "S'"
  }, 
  "Ahir Bhairav": {
    "aaroha": [
      "S", 
      "r", 
      "G", 
      "m", 
      "P", 
      "D", 
      "n", 
      "S'"
    ], 
    "avaroha": [
      "S'", 
      "n", 
      "D", 
      "P", 
      "m", 
      "G", 
      "r", 
      "S"
    ], 
    "jati": "Sampurna-Sampurna", 
    "pakad": [
      "S", 
      "r", 
      "G", 
      "M", 
      "G", 
      "M", 
      "r", 
      "\u1e47", 
      "\u1e0c", 
      "\u1e47", 
      "r", 
      "S"
    ], 
    "samvadi": "S", 
    "thaat": "Bhairav", 
    "time": "At daybreak, 6-9", 
    "vadi": "m"
  }, 
  "Ahiri": {
    "aaroha": [
      "S", 
      "r", 
      "g", 
      "m", 
      "P", 
      "D", 
      "n", 
      "S'"
    ], 
    "avaroha": [
      "S'", 
      "N", 
      "D", 
      "P", 
      "m", 
      "G", 
      "R", 
      "S"
    ], 
    "jati": "Sampurna-Sampurna", 
    "pakad": [
      "P", 
      "D", 
      "n", 
      "D", 
      "m", 
      "g", 
      "r", 
      "g", 
      "S"
    ], 
    "samvadi": "S", 
    "thaat": "Bhairavi", 
    "time": "Morning, 6-9", 
    "vadi": "m"
  }, 
  "Alhaiya Bilaval": {
    "aaroha": [
      "S", 
      "G", 
      "R", 
      "G", 
      "P", 
      "N", 
      "D", 
      "N", 
      "S'"
    ], 
    "avaroha": [
      "S'", 
      "N", 
      "D", 
      "n", 
      "D", 
      "P", 
      "M", 
      "G", 
      "M", 
      "R", 
      "S"
    ], 
    "jati": "Sampurna", 
    "pakad": [
      "G", 
      "R", 
      "P", 
      "D", 
      "N", 
      "S"
    ], 
    "samvadi": "G", 
    "thaat": "Bilaval", 
    "time": "Late Morning, 9-12", 
    "vadi": "D"
  }, 
  "Amritavarshini": {
    "aaroha": [
      "S", 
      "G", 
      "M", 
      "P", 
      "N", 
      "S'"
    ], 
    "avaroha": [
      "S'", 
      "N", 
      "P", 
      "M", 
      "G", 
      "S"
    ], 
    "jati": "Audav-Audav", 
    "pakad": [
      "G", 
      "M", 
      "P", 
      "N", 
      "S'", 
      "N", 
      "P", 
      "M", 
      "P", 
      "G", 
      "M", 
      "P"
    ], 
    "samvadi": "S", 
    "thaat": "Kalyaan", 
    "time": "Evening, 6-9", 
    "vadi": "P"
  }, 
  "Anandbhairavi": {
    "aaroha": [
      "S", 
      "r", 
      "G", 
      "m", 
      "P", 
      "m", 
      "P", 
      "D", 
      "N", 
      "S'"
    ], 
    "avaroha": [
      "S'", 
      "D", 
      "n", 
      "P", 
      "m", 
      "G", 
      "m", 
      "r", 
      "S"
    ], 
    "jati": "Audav-Sampurna", 
    "pakad": [
      "r", 
      "G", 
      "m", 
      "P", 
      "S'", 
      "D", 
      "n", 
      "P", 
      "m", 
      "G", 
      "m", 
      "r"
    ], 
    "samvadi": "S", 
    "thaat": "Bhairavi", 
    "time": "Morning, 6-9", 
    "vadi": "m"
  }, 
  "Asavari": {
    "aaroha": [
      "S", 
      "R", 
      "m", 
      "P", 
      "d", 
      "S'"
    ], 
    "avaroha": [
      "S'", 
      "n", 
      "D", 
      "P", 
      "m", 
      "G", 
      "r", 
      "S"
    ], 
    "jati": "Audav-Sampurna", 
    "pakad": [
      "R", 
      "m", 
      "P", 
      "n", 
      "D", 
      "P"
    ], 
    "samvadi": "g", 
    "thaat": "Asavari", 
    "time": "Late Morning, 9-12", 
    "vadi": "d"
  }, 
  "Asavari sindhura": {
    "aaroha": [
      "S", 
      "R", 
      "m", 
      "P", 
      "D", 
      "S'"
    ], 
    "avaroha": [
      "S'", 
      "n", 
      "D", 
      "P", 
      "d", 
      "m", 
      "P", 
      "g", 
      "R", 
      "m", 
      "m", 
      "g", 
      "S", 
      "R", 
      "S"
    ], 
    "jati": "Audav-Sampurna", 
    "pakad": [
      "m", 
      "P", 
      "D", 
      "S'", 
      "n", 
      "d", 
      "P", 
      "D", 
      "m", 
      "P", 
      "D", 
      "S'"
    ], 
    "samvadi": "P", 
    "thaat": "Asavari", 
    "time": "Morning, 9-12", 
    "vadi": "S'"
  }, 
  "Badhans": {
    "aaroha": [
      "S", 
      "R", 
      "m", 
      "R", 
      "m", 
      "P", 
      "N", 
      "S'"
    ], 
    "avaroha": [
      "S", 
      "n", 
      "P", 
      "m", 
      "P", 
      "m", 
      "R", 
      "R", 
      "'N", 
      "S"
    ], 
    "jati": "Audav-Shadav", 
    "pakad": [
      "S", 
      "R", 
      "m", 
      "n", 
      "P", 
      "m", 
      "R", 
      "m", 
      "'N", 
      "R", 
      "S"
    ], 
    "samvadi": "P", 
    "thaat": "Khamaj", 
    "time": "Afternoon, 12-3", 
    "vadi": "R"
  }, 
  "Bageshri": {
    "aaroha": [
      "N", 
      "S", 
      "g", 
      "m", 
      "D", 
      "n", 
      "S"
    ], 
    "avaroha": [
      "S'", 
      "n", 
      "D", 
      "m", 
      "P", 
      "D", 
      "g", 
      "m", 
      "g", 
      "R", 
      "S"
    ], 
    "jati": "Audav-Sampurna", 
    "pakad": [
      "D", 
      "n", 
      "s", 
      "m", 
      "m", 
      "P", 
      "D", 
      "m", 
      "g", 
      "R", 
      "S"
    ], 
    "samvadi": "S", 
    "thaat": "Kafi", 
    "time": "Around Midnight, 12-3", 
    "vadi": "m"
  }, 
  "Bahar": {
    "aaroha": [
      "n", 
      "S", 
      "m", 
      "m", 
      "P", 
      "g", 
      "m", 
      "n", 
      "D", 
      "N", 
      "S"
    ], 
    "avaroha": [
      "S'", 
      "n", 
      "P", 
      "m", 
      "P", 
      "g", 
      "m", 
      "R", 
      "S"
    ], 
    "jati": "Shadav-Shadav", 
    "pakad": [
      "S", 
      "m", 
      "m", 
      "P", 
      "g", 
      "m", 
      "n", 
      "D", 
      "N", 
      "S'"
    ], 
    "samvadi": "S", 
    "thaat": "Kafi", 
    "time": "Around Midnight, 12-3", 
    "vadi": "m"
  }, 
  "Bahar basanth": {
    "aaroha": [
      "S", 
      "m", 
      "m", 
      "P", 
      "g", 
      "m", 
      "n", 
      "D", 
      "N", 
      "S'"
    ], 
    "avaroha": [
      "S'", 
      "N", 
      "d", 
      "P", 
      "M", 
      "G", 
      "M", 
      "G", 
      "M", 
      "G", 
      "r", 
      "S"
    ], 
    "jati": "mishra/Sankeerna", 
    "pakad": [
      "S", 
      "m", 
      "P", 
      "g", 
      "m", 
      "n", 
      "D", 
      "N", 
      "S'", 
      "N", 
      "d", 
      "S'", 
      "N", 
      "d", 
      "P", 
      "M", 
      "G", 
      "M", 
      "G", 
      "M", 
      "G", 
      "r", 
      "S"
    ], 
    "samvadi": "P", 
    "thaat": "Poorvi", 
    "time": "Late Night, 12-3", 
    "vadi": "S'"
  }, 
  "Bangalbhairav": {
    "aaroha": [
      "S", 
      "r", 
      "G", 
      "m", 
      "P", 
      "d", 
      "S'"
    ], 
    "avaroha": [
      "S'", 
      "d", 
      "P", 
      "m", 
      "P", 
      "G", 
      "m", 
      "r", 
      "S"
    ], 
    "jati": "Shadav-Shadav", 
    "pakad": [
      "S", 
      "'d", 
      "S", 
      "S", 
      "r", 
      "d", 
      "d", 
      "P", 
      "G", 
      "m", 
      "r", 
      "s"
    ], 
    "samvadi": "r", 
    "thaat": "Bhairav", 
    "time": "At daybreak, 6-9", 
    "vadi": "d"
  }, 
  "Barari": {
    "aaroha": [
      "S", 
      "'N", 
      "r", 
      "G", 
      "r", 
      "G", 
      "P", 
      "M", 
      "D", 
      "S"
    ], 
    "avaroha": [
      "S'", 
      "N", 
      "r", 
      "N", 
      "D", 
      "M", 
      "G", 
      "P", 
      "G", 
      "r", 
      "S"
    ], 
    "jati": "Shadav-Sampoorna", 
    "pakad": [
      "S", 
      "P", 
      "G", 
      "r", 
      "G", 
      "P", 
      "M", 
      "D", 
      "S'", 
      "r'", 
      "N", 
      "D", 
      "P", 
      "G", 
      "r", 
      "S"
    ], 
    "samvadi": "D", 
    "thaat": "Marva", 
    "time": "Evening, 6-9", 
    "vadi": "G"
  }, 
  "Barva": {
    "aaroha": [
      "S", 
      "R", 
      "m", 
      "P", 
      "D", 
      "N", 
      "S'"
    ], 
    "avaroha": [
      "S'", 
      "n", 
      "D", 
      "P", 
      "m", 
      "P", 
      "g", 
      "R", 
      "g", 
      "S"
    ], 
    "jati": "Audav-Sampurna", 
    "pakad": [
      "G", 
      "R", 
      "g", 
      "S", 
      "N'", 
      "S", 
      "R", 
      "m", 
      "P", 
      "D", 
      "m", 
      "G", 
      "R", 
      "g", 
      "S"
    ], 
    "samvadi": "P", 
    "thaat": "Kafi", 
    "time": "Afternoon, 12-3", 
    "vadi": "S'"
  }, 
  "Basant": {
    "aaroha": [
      "S", 
      "G", 
      "M", 
      "d", 
      "r'", 
      "S'"
    ], 
    "avaroha": [
      "S'", 
      "N", 
      "d", 
      "P", 
      "M", 
      "G", 
      "M", 
      "G", 
      "r", 
      "S"
    ], 
    "jati": "Audav-Sampurna", 
    "pakad": [
      "M", 
      "d", 
      "r'", 
      "S'", 
      "N", 
      "d", 
      "P", 
      "M", 
      "G", 
      "M", 
      "G"
    ], 
    "samvadi": "P", 
    "thaat": "Poorvi", 
    "time": "Spring Season , 3-6", 
    "vadi": "S'"
  }, 
  "Bengali": {
    "aaroha": [
      "S", 
      "R", 
      "m", 
      "P", 
      "D", 
      "S'"
    ], 
    "avaroha": [
      "R'", 
      "N", 
      "P", 
      "D", 
      "m", 
      "P", 
      "G", 
      "S"
    ], 
    "jati": "Shadav-Sampoorna", 
    "pakad": [
      "S", 
      "R", 
      "m", 
      "P", 
      "D", 
      "m", 
      "P", 
      "G", 
      "S", 
      "R", 
      "P", 
      "m"
    ], 
    "samvadi": "P", 
    "thaat": "Bilaval", 
    "time": "Monsoon", 
    "vadi": "S"
  }, 
  "Bhairav": {
    "aaroha": [
      "S", 
      "G", 
      "m", 
      "P", 
      "G", 
      "m", 
      "d", 
      "S'"
    ], 
    "avaroha": [
      "S'", 
      "N", 
      "S'", 
      "d", 
      "P", 
      "G", 
      "m", 
      "P", 
      "G", 
      "m", 
      "r", 
      "S"
    ], 
    "jati": "Sampurna", 
    "pakad": [
      "S", 
      "G", 
      "m", 
      "P", 
      "G", 
      "m", 
      "d", 
      "P", 
      "G", 
      "m", 
      "P", 
      "G", 
      "m", 
      "r", 
      "S"
    ], 
    "samvadi": "r", 
    "thaat": "Bhairav", 
    "time": "At daybreak, 6-9", 
    "vadi": "d"
  }, 
  "Bhairavi": {
    "aaroha": [
      "S", 
      "r", 
      "g", 
      "m", 
      "P", 
      "d", 
      "n", 
      "S'"
    ], 
    "avaroha": [
      "S'", 
      "n", 
      "d", 
      "P", 
      "m", 
      "g", 
      "r", 
      "S"
    ], 
    "jati": "Sampurna", 
    "pakad": [
      "n", 
      "S", 
      "g", 
      "m", 
      "d", 
      "P", 
      "g", 
      "m", 
      "P", 
      "g", 
      "m", 
      "r", 
      "S"
    ], 
    "samvadi": "S", 
    "thaat": "Bhairavi", 
    "time": "Morning/concert end,6-9", 
    "vadi": "P"
  }, 
  "Bhankar": {
    "aaroha": [
      "N", 
      "r", 
      "S", 
      "G", 
      "m", 
      "P", 
      "G", 
      "M", 
      "D", 
      "M", 
      "G", 
      "M", 
      "D", 
      "S", 
      "N", 
      "r'", 
      "S'"
    ], 
    "avaroha": [
      "S'", 
      "r'", 
      "N", 
      "D", 
      "M", 
      "m", 
      "G", 
      "m", 
      "G", 
      "r", 
      "S"
    ], 
    "jati": "Sampurna", 
    "pakad": [
      "S'", 
      "r'", 
      "N", 
      "D", 
      "M", 
      "m", 
      "G", 
      "m", 
      "r", 
      "S"
    ], 
    "samvadi": "S", 
    "thaat": "Bhairav", 
    "time": "At daybreak, 3-6", 
    "vadi": "P"
  }, 
  "Bhatiyar": {
    "aaroha": [
      "S", 
      "r", 
      "S", 
      "S", 
      "m", 
      "P", 
      "G", 
      "M", 
      "D", 
      "S'"
    ], 
    "avaroha": [
      "S'", 
      "r'", 
      "N", 
      "D", 
      "P", 
      "D", 
      "P", 
      "m", 
      "P", 
      "G", 
      "r", 
      "S"
    ], 
    "jati": "Sampurna-Sampurna", 
    "pakad": [
      "S", 
      "D", 
      "m", 
      "P", 
      "G", 
      "P", 
      "G", 
      "r", 
      "S"
    ], 
    "samvadi": "S", 
    "thaat": "Bhairav", 
    "time": "Early Morning, 3-6", 
    "vadi": "m"
  }, 
  "Bhim": {
    "aaroha": [
      "S", 
      "G", 
      "m", 
      "P", 
      "n", 
      "S'"
    ], 
    "avaroha": [
      "g'", 
      "R'", 
      "S'", 
      "n", 
      "D", 
      "m", 
      "D", 
      "m", 
      "G", 
      "R", 
      "S"
    ], 
    "jati": "Audav-Sampurna", 
    "pakad": [
      "n", 
      "S'", 
      "g'", 
      "R'", 
      "S'", 
      "n", 
      "D", 
      "m", 
      "G", 
      "R", 
      "S"
    ], 
    "samvadi": "P", 
    "thaat": "Kafi", 
    "time": "Afternoon, 12-3", 
    "vadi": "S"
  }, 
  "Bhimpalasi": {
    "aaroha": [
      "N", 
      "S", 
      "g", 
      "m", 
      "P", 
      "n", 
      "S'"
    ], 
    "avaroha": [
      "S'", 
      "n", 
      "D", 
      "P", 
      "m", 
      "g", 
      "R", 
      "S"
    ], 
    "jati": "Audav-Sampurna", 
    "pakad": [
      "N", 
      "S", 
      "g", 
      "m", 
      "P", 
      "g", 
      "m", 
      "g", 
      "R", 
      "n", 
      "S"
    ], 
    "samvadi": "S", 
    "thaat": "Kafi", 
    "time": "Early Afternoon, 12-3", 
    "vadi": "m"
  }, 
  "Bhoopal-Todi": {
    "aaroha": [
      "S", 
      "r", 
      "g", 
      "P", 
      "d", 
      "S"
    ], 
    "avaroha": [
      "S", 
      "d", 
      "P", 
      "g", 
      "r", 
      "S"
    ], 
    "jati": "Audav-Audav", 
    "pakad": [
      "S", 
      "r", 
      "d", 
      "S", 
      "r", 
      "g", 
      "r", 
      "S"
    ], 
    "samvadi": "g", 
    "thaat": "Bhairavi", 
    "time": "Morning, 6-9", 
    "vadi": "d"
  }, 
  "Bhoopali": {
    "aaroha": [
      "S", 
      "R", 
      "G", 
      "P", 
      "D", 
      "S'"
    ], 
    "avaroha": [
      "S'", 
      "D", 
      "P", 
      "G", 
      "R", 
      "S"
    ], 
    "jati": "Audav-Audav", 
    "pakad": [
      "S", 
      "G", 
      "R", 
      "S\u2018", 
      "D", 
      "S", 
      "R", 
      "G"
    ], 
    "samvadi": "D", 
    "thaat": "Kalyaan", 
    "time": "Early Night, 9-12", 
    "vadi": "G"
  }, 
  "Bhup": {
    "aaroha": [
      "S", 
      "R", 
      "G", 
      "P", 
      "D", 
      "S'"
    ], 
    "avaroha": [
      "S'", 
      "D", 
      "P", 
      "G", 
      "R", 
      "S"
    ], 
    "jati": "Audav-Audav", 
    "pakad": [
      "S", 
      "R", 
      "G", 
      "R", 
      "G", 
      "R", 
      "G", 
      "R", 
      "P", 
      "G", 
      "R", 
      "G", 
      "S", 
      "R", 
      "'D", 
      "S"
    ], 
    "samvadi": "D", 
    "thaat": "Kalyaan", 
    "time": "Evening, 6-9", 
    "vadi": "G"
  }, 
  "Bibhas": {
    "aaroha": [
      "S", 
      "r", 
      "G", 
      "P", 
      "d", 
      "S'"
    ], 
    "avaroha": [
      "S'", 
      "d", 
      "P", 
      "G", 
      "r", 
      "S"
    ], 
    "jati": "Audav-Audav", 
    "pakad": [
      "G", 
      "P", 
      "d", 
      "G", 
      "P", 
      "G", 
      "r", 
      "S"
    ], 
    "samvadi": "G", 
    "thaat": "Marva", 
    "time": "At daybreak", 
    "vadi": "d"
  }, 
  "Bihag": {
    "aaroha": [
      "N", 
      "S", 
      "G", 
      "m", 
      "P", 
      "N", 
      "S"
    ], 
    "avaroha": [
      "S'", 
      "N", 
      "D", 
      "P", 
      "M", 
      "P", 
      "G", 
      "m", 
      "G", 
      "R", 
      "S"
    ], 
    "jati": "Audav-Shadav", 
    "pakad": [
      "P", 
      "G", 
      "m", 
      "G", 
      "R", 
      "S"
    ], 
    "samvadi": "N", 
    "thaat": "Bilaval", 
    "time": "Late Night, 12-3", 
    "vadi": "G"
  }, 
  "Bihagda": {
    "aaroha": [
      "N", 
      "S", 
      "G", 
      "m", 
      "P", 
      "N", 
      "S'"
    ], 
    "avaroha": [
      "S'", 
      "N", 
      "D", 
      "P", 
      "n", 
      "D", 
      "P", 
      "D", 
      "G", 
      "m", 
      "G", 
      "R", 
      "S"
    ], 
    "jati": "Audav-Sampurna", 
    "pakad": [
      "n", 
      "D", 
      "P", 
      "D", 
      "G", 
      "m", 
      "G", 
      "R", 
      "S"
    ], 
    "samvadi": "N", 
    "thaat": "Bilaval", 
    "time": "Night, 9-12", 
    "vadi": "G"
  }, 
  "Bilaskhani Todi": {
    "aaroha": [
      "S", 
      "r", 
      "G", 
      "P", 
      "d", 
      "S'"
    ], 
    "avaroha": [
      "S'", 
      "r'", 
      "n", 
      "d", 
      "m", 
      "g", 
      "r", 
      "g", 
      "r", 
      "S"
    ], 
    "jati": "Audav-Sampurna", 
    "pakad": [
      "S'", 
      "r'", 
      "n", 
      "d", 
      "g", 
      "P", 
      "d", 
      "n", 
      "d", 
      "m", 
      "g", 
      "r", 
      "g", 
      "r", 
      "S"
    ], 
    "samvadi": "g", 
    "thaat": "Bhairavi", 
    "time": "Morning, 6-9", 
    "vadi": "d"
  }, 
  "Brindabani Sarang": {
    "aaroha": [
      "N", 
      "S", 
      "R", 
      "m", 
      "P", 
      "N", 
      "S'"
    ], 
    "avaroha": [
      "S", 
      "n", 
      "P", 
      "m", 
      "R", 
      "N'", 
      "S"
    ], 
    "jati": "Audav-Audav", 
    "pakad": [
      "n", 
      "P", 
      "m", 
      "R", 
      "m", 
      "R", 
      "'N", 
      "S"
    ], 
    "samvadi": "P", 
    "thaat": "Kafi", 
    "time": "Early Afternoon, 12-3", 
    "vadi": "R"
  }, 
  "Chandni,Kedar": {
    "aaroha": [
      "S", 
      "m", 
      "M", 
      "M", 
      "P", 
      "D", 
      "N", 
      "S'"
    ], 
    "avaroha": [
      "S'", 
      "N", 
      "D", 
      "P", 
      "D", 
      "P", 
      "M", 
      "m", 
      "R", 
      "S"
    ], 
    "jati": "Audav-Shadav", 
    "pakad": [
      "D", 
      "N", 
      "D", 
      "P", 
      "D", 
      "P", 
      "M", 
      "m", 
      "R", 
      "S"
    ], 
    "samvadi": "S", 
    "thaat": "Kalyaan", 
    "time": "Night, 9-12", 
    "vadi": "m"
  }, 
  "Chandrakanth": {
    "aaroha": [
      "S", 
      "R", 
      "G", 
      "P", 
      "D", 
      "N", 
      "S'"
    ], 
    "avaroha": [
      "S'", 
      "N", 
      "D", 
      "P", 
      "M", 
      "G", 
      "R", 
      "S"
    ], 
    "jati": "Shadav-Sampoorna", 
    "pakad": [
      "G", 
      "M", 
      "P", 
      "D", 
      "P", 
      "M", 
      "G", 
      "R", 
      "S"
    ], 
    "samvadi": "N", 
    "thaat": "Kalyaan", 
    "time": "Early Night, 9-12", 
    "vadi": "G"
  }, 
  "Chandrakauns": {
    "aaroha": [
      "S", 
      "g", 
      "m", 
      "d", 
      "N", 
      "S'"
    ], 
    "avaroha": [
      "S'", 
      "R'", 
      "S'", 
      "N", 
      "d", 
      "m", 
      "g", 
      "S"
    ], 
    "jati": "Audav-Audav", 
    "pakad": [
      "g", 
      "m", 
      "g", 
      "'N", 
      "g", 
      "S"
    ], 
    "samvadi": "S", 
    "thaat": "Bhairavi", 
    "time": "Late Night, 12-3", 
    "vadi": "m"
  }, 
  "Chhayanat": {
    "aaroha": [
      "S", 
      "R", 
      "G", 
      "m", 
      "P", 
      "R", 
      "G", 
      "m", 
      "D", 
      "P", 
      "P", 
      "S'", 
      "N", 
      "S'"
    ], 
    "avaroha": [
      "R'", 
      "S'", 
      "N", 
      "D", 
      "P", 
      "R", 
      "G", 
      "M", 
      "R", 
      "S"
    ], 
    "jati": "Shadav-Sampoorna", 
    "pakad": [
      "P", 
      "R", 
      "G", 
      "m", 
      "P", 
      "m", 
      "G", 
      "m", 
      "R", 
      "S"
    ], 
    "samvadi": "P", 
    "thaat": "Kalyaan", 
    "time": "Early Night, 9-12", 
    "vadi": "R"
  }, 
  "Darbari Kanada": {
    "aaroha": [
      "S", 
      "r", 
      "g", 
      "m", 
      "P", 
      "d", 
      "n", 
      "S'"
    ], 
    "avaroha": [
      "R'", 
      "n", 
      "S'", 
      "d", 
      "n", 
      "P", 
      "m", 
      "P", 
      "g", 
      "m", 
      "R", 
      "S"
    ], 
    "jati": "Sampurna-Sampurna", 
    "pakad": [
      "S", 
      "R", 
      "g", 
      "R", 
      "S", 
      "'d", 
      "'n", 
      "R", 
      "S"
    ], 
    "samvadi": "P", 
    "thaat": "Asavari", 
    "time": "Midnight, 9-12", 
    "vadi": "R"
  }, 
  "Deepak Kedar": {
    "aaroha": [
      "S", 
      "R", 
      "M", 
      "P", 
      "D", 
      "P", 
      "S'"
    ], 
    "avaroha": [
      "S'", 
      "N", 
      "P", 
      "M", 
      "P", 
      "m", 
      "R", 
      "S"
    ], 
    "jati": "Audav-Audav", 
    "pakad": [
      "S", 
      "R", 
      "M", 
      "P", 
      "D", 
      "P", 
      "m", 
      "R", 
      "S"
    ], 
    "samvadi": "S'", 
    "thaat": "Kalyaan", 
    "time": "Night, 6-9", 
    "vadi": "P"
  }, 
  "Desh": {
    "aaroha": [
      "N", 
      "S", 
      "R", 
      "m", 
      "P", 
      "N", 
      "S'"
    ], 
    "avaroha": [
      "N", 
      "S'", 
      "R'", 
      "n", 
      "D", 
      "P", 
      "D", 
      "m", 
      "G", 
      "R", 
      "G", 
      "'N", 
      "S"
    ], 
    "jati": "Audav-Sampurna", 
    "pakad": [
      "R", 
      "m", 
      "P", 
      "n", 
      "D", 
      "P", 
      "D", 
      "m", 
      "G", 
      "R", 
      "G", 
      "'N", 
      "S"
    ], 
    "samvadi": "P", 
    "thaat": "Khamaj", 
    "time": "Late Night, 12-3", 
    "vadi": "R"
  }, 
  "Deshkar": {
    "aaroha": [
      "S", 
      "R", 
      "G", 
      "P", 
      "D", 
      "S'"
    ], 
    "avaroha": [
      "S'", 
      "D", 
      "P", 
      "D", 
      "P", 
      "G", 
      "R", 
      "'D", 
      "S"
    ], 
    "jati": "Audav-Audav", 
    "pakad": [
      "S", 
      "D", 
      "P", 
      "D", 
      "S'", 
      "D", 
      "P", 
      "D", 
      "G", 
      "P", 
      "G", 
      "P", 
      "D", 
      "P", 
      "G", 
      "R", 
      "S", 
      "R'", 
      "D", 
      "S"
    ], 
    "samvadi": "G", 
    "thaat": "Bilaval", 
    "time": "Late Morning, 9-12", 
    "vadi": "D"
  }, 
  "Desi": {
    "aaroha": [
      "S", 
      "R", 
      "m", 
      "P", 
      "m", 
      "P", 
      "n", 
      "S'"
    ], 
    "avaroha": [
      "S'", 
      "P", 
      "D", 
      "P", 
      "d", 
      "m", 
      "P", 
      "R", 
      "g", 
      "S", 
      "R", 
      "'n", 
      "S"
    ], 
    "jati": "Audav-Sampurna", 
    "pakad": [
      "P", 
      "D", 
      "m", 
      "P", 
      "g", 
      "r", 
      "S", 
      "r", 
      "'n", 
      "S"
    ], 
    "samvadi": "R", 
    "thaat": "Asavari", 
    "time": "Late Morning, 9-12", 
    "vadi": "P"
  }, 
  "Dev gandhar": {
    "aaroha": [
      "S", 
      "R", 
      "m", 
      "P", 
      "d", 
      "m", 
      "P", 
      "d", 
      "n", 
      "S'"
    ], 
    "avaroha": [
      "S'", 
      "n", 
      "d", 
      "P", 
      "m", 
      "P", 
      "g", 
      "R", 
      "S", 
      "R", 
      "n", 
      "S", 
      "R", 
      "G", 
      "m", 
      "P", 
      "g", 
      "R", 
      "S"
    ], 
    "jati": "Shadav-Sampoorna", 
    "pakad": [
      "m", 
      "P", 
      "d", 
      "m", 
      "P", 
      "g", 
      "R", 
      "S", 
      "R", 
      "n", 
      "S", 
      "R", 
      "G", 
      "m"
    ], 
    "samvadi": "G", 
    "thaat": "Asavari", 
    "time": "Morning, 9-12", 
    "vadi": "d"
  }, 
  "Devagiribilaval": {
    "aaroha": [
      "S", 
      "R", 
      "G", 
      "P", 
      "N", 
      "D", 
      "N", 
      "S"
    ], 
    "avaroha": [
      "S", 
      "N", 
      "D", 
      "P", 
      "P", 
      "m", 
      "G", 
      "R", 
      "'N", 
      "R", 
      "'N", 
      "R", 
      "G", 
      "m", 
      "G", 
      "G", 
      "R", 
      "S"
    ], 
    "jati": "Shadav-Sampoorna", 
    "pakad": [
      "G", 
      "m", 
      "G", 
      "R", 
      "'N", 
      "R", 
      "'N", 
      "G", 
      "G", 
      "R", 
      "'N", 
      "S"
    ], 
    "samvadi": "P", 
    "thaat": "Bilaval", 
    "time": "Morning, 6-9", 
    "vadi": "S"
  }, 
  "Devaranjani": {
    "aaroha": [
      "S", 
      "m", 
      "m", 
      "P", 
      "d", 
      "N", 
      "S'"
    ], 
    "avaroha": [
      "S'", 
      "N", 
      "d", 
      "n", 
      "P", 
      "d", 
      "m", 
      "n", 
      "S"
    ], 
    "jati": "Audav-Audav", 
    "pakad": [
      "S", 
      "m", 
      "m", 
      "P", 
      "d", 
      "N", 
      "S'", 
      "d", 
      "P", 
      "m", 
      "S"
    ], 
    "samvadi": "S", 
    "thaat": "Bhairav", 
    "time": "Morning, 6-9", 
    "vadi": "m"
  }, 
  "Devgiri": {
    "aaroha": [
      "S", 
      "R", 
      "G", 
      "P", 
      "N", 
      "D", 
      "N", 
      "S'"
    ], 
    "avaroha": [
      "S", 
      "N", 
      "D", 
      "P", 
      "P", 
      "m", 
      "G", 
      "R", 
      "N'", 
      "R", 
      "N'", 
      "R", 
      "G", 
      "m", 
      "G", 
      "G", 
      "R", 
      "S"
    ], 
    "jati": "Shadav-Sampoorna", 
    "pakad": [
      "G", 
      "m", 
      "G", 
      "R", 
      "'N", 
      "R", 
      "'N", 
      "G", 
      "G", 
      "R", 
      "'N", 
      "S"
    ], 
    "samvadi": "P", 
    "thaat": "Bilaval", 
    "time": "Morning, 6-9", 
    "vadi": "S"
  }, 
  "Dhanabasanti": {
    "aaroha": [
      "S", 
      "G", 
      "M", 
      "d", 
      "N", 
      "S"
    ], 
    "avaroha": [
      "S", 
      "N", 
      "d", 
      "P", 
      "M", 
      "G", 
      "M", 
      "G", 
      "G", 
      "M", 
      "r", 
      "G", 
      "M", 
      "G", 
      "r", 
      "S"
    ], 
    "jati": "Audav-Sampurna", 
    "pakad": [
      "M", 
      "d", 
      "S", 
      "N", 
      "d", 
      "P", 
      "M", 
      "G", 
      "M", 
      "G", 
      "G", 
      "M", 
      "r", 
      "G", 
      "M", 
      "G", 
      "r", 
      "S", 
      "S", 
      "m", 
      "G", 
      "M", 
      "d", 
      "N", 
      "S"
    ], 
    "samvadi": "S", 
    "thaat": "Poorvi", 
    "time": "Evening, 6-9", 
    "vadi": "P"
  }, 
  "Dhanashree": {
    "aaroha": [
      "n", 
      "S", 
      "g", 
      "m", 
      "P", 
      "n", 
      "S'"
    ], 
    "avaroha": [
      "S'", 
      "n", 
      "D", 
      "P", 
      "m", 
      "g", 
      "R", 
      "S"
    ], 
    "jati": "Audav-Sampurna", 
    "pakad": [
      "'n", 
      "S", 
      "g", 
      "m", 
      "P", 
      "g", 
      "m", 
      "g", 
      "R", 
      "n", 
      "S"
    ], 
    "samvadi": "S", 
    "thaat": "Kafi", 
    "time": "Late Evening, 3-6", 
    "vadi": "P"
  }, 
  "Dhani": {
    "aaroha": [
      "n", 
      "S", 
      "g", 
      "m", 
      "P", 
      "n", 
      "S'"
    ], 
    "avaroha": [
      "S'", 
      "n", 
      "P", 
      "m", 
      "g", 
      "R", 
      "S"
    ], 
    "jati": "Audav-Shadav", 
    "pakad": [
      "g", 
      "m", 
      "n", 
      "P", 
      "g", 
      "R", 
      "S"
    ], 
    "samvadi": "n", 
    "thaat": "Kafi", 
    "time": "Any time day or night", 
    "vadi": "g"
  }, 
  "Durga": {
    "aaroha": [
      "S", 
      "R", 
      "m", 
      "P", 
      "D", 
      "S'"
    ], 
    "avaroha": [
      "S'", 
      "D", 
      "P", 
      "D", 
      "m", 
      "R", 
      "'D", 
      "S"
    ], 
    "jati": "Audav-Audav", 
    "pakad": [
      "m", 
      "P", 
      "D", 
      "P", 
      "D", 
      "m", 
      "R", 
      "P", 
      "m", 
      "R", 
      "'D", 
      "S"
    ], 
    "samvadi": "S", 
    "thaat": "Bilaval", 
    "time": "Late Night, 12-3", 
    "vadi": "m"
  }, 
  "Gaara": {
    "aaroha": [
      "S", 
      "G", 
      "m", 
      "P", 
      "D", 
      "N", 
      "S'"
    ], 
    "avaroha": [
      "S'", 
      "n", 
      "D", 
      "P", 
      "m", 
      "g", 
      "R", 
      "S", 
      "'N", 
      "S", 
      "'n", 
      "'D", 
      "S"
    ], 
    "jati": "Mishra/Sankeerna", 
    "pakad": [
      "'N", 
      "S", 
      "R", 
      "'n", 
      "'D", 
      "'D", 
      "'n", 
      "'S", 
      "'N", 
      "'S", 
      "'D", 
      "'n", 
      "S", 
      "R", 
      "G", 
      "R", 
      "S", 
      "R", 
      "m", 
      "g", 
      "R", 
      "S", 
      "'D", 
      "'n", 
      "'D", 
      "S"
    ], 
    "samvadi": "P", 
    "thaat": "Kafi", 
    "time": "No specific time", 
    "vadi": "S"
  }, 
  "Gandhari": {
    "aaroha": [
      "S", 
      "R", 
      "m", 
      "P", 
      "d", 
      "n", 
      "S'"
    ], 
    "avaroha": [
      "S'", 
      "n", 
      "d", 
      "n", 
      "d", 
      "P", 
      "m", 
      "g", 
      "r", 
      "s"
    ], 
    "jati": "Shadav-Sampoorna", 
    "pakad": [
      "R", 
      "m", 
      "P", 
      "d", 
      "P", 
      "n", 
      "d", 
      "S", 
      "n", 
      "d", 
      "P"
    ], 
    "samvadi": "g", 
    "thaat": "Asavari", 
    "time": "Late Morning, 9-12", 
    "vadi": "d"
  }, 
  "Gaud Malhar": {
    "aaroha": [
      "S", 
      "R", 
      "G", 
      "m", 
      "R", 
      "P", 
      "m", 
      "P", 
      "n", 
      "D", 
      "N", 
      "S'"
    ], 
    "avaroha": [
      "S'", 
      "D", 
      "n", 
      "P", 
      "m", 
      "P", 
      "m", 
      "R", 
      "G", 
      "R", 
      "S"
    ], 
    "jati": "Sampurna", 
    "pakad": [
      "S", 
      "R", 
      "G", 
      "m", 
      "m", 
      "R", 
      "P", 
      "n", 
      "D", 
      "n", 
      "P", 
      "m", 
      "G", 
      "m", 
      "R", 
      "S"
    ], 
    "samvadi": "S", 
    "thaat": "Khamaj", 
    "time": "Any time in rainy season", 
    "vadi": "m"
  }, 
  "Gaud Sarang": {
    "aaroha": [
      "N", 
      "S", 
      "G", 
      "R", 
      "m", 
      "G", 
      "P", 
      "M", 
      "D", 
      "P", 
      "N", 
      "D", 
      "S'"
    ], 
    "avaroha": [
      "S'", 
      "D", 
      "P", 
      "M", 
      "P", 
      "G", 
      "m", 
      "R", 
      "G", 
      "R", 
      "m", 
      "G", 
      "P", 
      "R", 
      "S"
    ], 
    "jati": "Sampurna-Sampurna", 
    "pakad": [
      "G", 
      "R", 
      "m", 
      "G", 
      "P", 
      "R", 
      "S"
    ], 
    "samvadi": "D", 
    "thaat": "Kalyaan", 
    "time": "Early Afternoon, 12-3", 
    "vadi": "G"
  }, 
  "Gavati": {
    "aaroha": [
      "n", 
      "S", 
      "G", 
      "m", 
      "P", 
      "n", 
      "S'"
    ], 
    "avaroha": [
      "S", 
      "n", 
      "S'", 
      "D", 
      "P", 
      "m", 
      "P", 
      "G", 
      "m", 
      "R", 
      "S"
    ], 
    "jati": "Audav-Sampurna", 
    "pakad": [
      "P", 
      "n", 
      "S'", 
      "D", 
      "P", 
      "G", 
      "m", 
      "R", 
      "S"
    ], 
    "samvadi": "P", 
    "thaat": "Khamaj", 
    "time": "Afternoon, 3-6", 
    "vadi": "S"
  }, 
  "Gorakh Kalyan": {
    "aaroha": [
      "S", 
      "R", 
      "m", 
      "D", 
      "n", 
      "D", 
      "S'"
    ], 
    "avaroha": [
      "S'", 
      "n", 
      "D", 
      "m", 
      "R", 
      "R", 
      "m", 
      "P", 
      "m", 
      "R", 
      "'n", 
      "'D", 
      "S"
    ], 
    "jati": "Audav-Shadav", 
    "pakad": [
      "'D", 
      "S", 
      "R", 
      "m", 
      "R", 
      "'n", 
      "'D", 
      "S", 
      "m", 
      "D", 
      "n", 
      "D", 
      "m", 
      "R", 
      "R", 
      "m", 
      "P", 
      "m", 
      "R", 
      "'n", 
      "'D", 
      "S"
    ], 
    "samvadi": "m", 
    "thaat": "Khamaj", 
    "time": "Early Night, 9-12", 
    "vadi": "S"
  }, 
  "Gouri": {
    "aaroha": [
      "S", 
      "G", 
      "r", 
      "G", 
      "G", 
      "m", 
      "P", 
      "m", 
      "P", 
      "d", 
      "N", 
      "S'"
    ], 
    "avaroha": [
      "S'", 
      "N", 
      "D", 
      "P", 
      "d", 
      "P", 
      "m", 
      "G", 
      "G", 
      "r", 
      "'N", 
      "S", 
      "'N", 
      "S"
    ], 
    "jati": "Sampurna-Sampurna", 
    "pakad": [
      "m", 
      "d", 
      "P", 
      "d", 
      "m", 
      "P", 
      "G", 
      "m", 
      "r", 
      "G", 
      "r", 
      "S", 
      "r", 
      "S", 
      "'N"
    ], 
    "samvadi": "S", 
    "thaat": "Bhairav", 
    "time": "Evening, 6-9", 
    "vadi": "m"
  }, 
  "Gowri": {
    "aaroha": [
      "S", 
      "r", 
      "M", 
      "P", 
      "M", 
      "d", 
      "N", 
      "S'"
    ], 
    "avaroha": [
      "S'", 
      "N", 
      "d", 
      "P", 
      "d", 
      "m", 
      "P", 
      "M", 
      "d", 
      "M", 
      "G", 
      "r", 
      "G", 
      "r", 
      "S"
    ], 
    "jati": "Shadav-Sampoorna", 
    "pakad": [
      "N", 
      "d", 
      "P", 
      "d", 
      "m", 
      "M", 
      "d", 
      "M", 
      "G", 
      "r", 
      "G", 
      "r", 
      "S"
    ], 
    "samvadi": "S", 
    "thaat": "Poorvi", 
    "time": "Late Evening, 6-9", 
    "vadi": "P"
  }, 
  "Gujari Todi": {
    "aaroha": [
      "S", 
      "r", 
      "g", 
      "M", 
      "d", 
      "N", 
      "S'"
    ], 
    "avaroha": [
      "S'", 
      "N", 
      "d", 
      "M", 
      "g", 
      "r", 
      "S"
    ], 
    "jati": "Shadav-Shadav", 
    "pakad": [
      "M", 
      "d", 
      "N", 
      "d", 
      "M", 
      "g", 
      "r", 
      "g", 
      "r", 
      "S"
    ], 
    "samvadi": "r", 
    "thaat": "Todi", 
    "time": "Late Morning, 9-12", 
    "vadi": "d"
  }, 
  "Gunak(ri)ali": {
    "aaroha": [
      "S", 
      "r", 
      "m", 
      "P", 
      "d", 
      "S'"
    ], 
    "avaroha": [
      "S'", 
      "d", 
      "P", 
      "m", 
      "r", 
      "S"
    ], 
    "jati": "Audav-Audav", 
    "pakad": [
      "r", 
      "m", 
      "P", 
      "d", 
      "d", 
      "P", 
      "m", 
      "r", 
      "r", 
      "'d", 
      "S"
    ], 
    "samvadi": "r", 
    "thaat": "Bhairav", 
    "time": "At daybreak, 6-9", 
    "vadi": "d"
  }, 
  "Gunjikanada": {
    "aaroha": [
      "S", 
      "R", 
      "G", 
      "R", 
      "m", 
      "m", 
      "P", 
      "g", 
      "D", 
      "n", 
      "S'"
    ], 
    "avaroha": [
      "S'", 
      "D", 
      "n", 
      "P", 
      "g", 
      "g", 
      "m", 
      "R", 
      "S"
    ], 
    "jati": "Sampurna-Sampurna", 
    "pakad": [
      "S", 
      "'n", 
      "'n", 
      "S", 
      "S", 
      "R", 
      "g", 
      "g", 
      "m", 
      "R", 
      "S"
    ], 
    "samvadi": "S", 
    "thaat": "Kafi", 
    "time": "Night, 9-12", 
    "vadi": "P"
  }, 
  "Hamir": {
    "aaroha": [
      "S", 
      "R", 
      "G", 
      "m", 
      "D", 
      "N", 
      "S'"
    ], 
    "avaroha": [
      "S'", 
      "N", 
      "D", 
      "P", 
      "M", 
      "P", 
      "G", 
      "m", 
      "R", 
      "S"
    ], 
    "jati": "Shadav-Sampoorna", 
    "pakad": [
      "G", 
      "m", 
      "D", 
      "N", 
      "S'"
    ], 
    "samvadi": "G", 
    "thaat": "Kalyaan", 
    "time": "Early Night, 9-12", 
    "vadi": "D"
  }, 
  "Hamsadhwani": {
    "aaroha": [
      "S", 
      "R", 
      "G", 
      "P", 
      "N", 
      "S'"
    ], 
    "avaroha": [
      "S'", 
      "N", 
      "P", 
      "G", 
      "R", 
      "S"
    ], 
    "jati": "Audav-Audav", 
    "pakad": [
      "R", 
      "G", 
      "P", 
      "R", 
      "G", 
      "P", 
      "N", 
      "P", 
      "G", 
      "R", 
      "S"
    ], 
    "samvadi": "P", 
    "thaat": "Bilaval", 
    "time": "Early Night, 9-12", 
    "vadi": "S"
  }, 
  "Hamsakankini": {
    "aaroha": [
      "N", 
      "S", 
      "G", 
      "m", 
      "P", 
      "N", 
      "S'"
    ], 
    "avaroha": [
      "S", 
      "n", 
      "D", 
      "P", 
      "m", 
      "P", 
      "g", 
      "m", 
      "P", 
      "g", 
      "R", 
      "S", 
      "'N", 
      "'N", 
      "S"
    ], 
    "jati": "Audav-Sampurna", 
    "pakad": [
      "S'", 
      "G", 
      "m", 
      "P", 
      "P", 
      "n", 
      "D", 
      "P", 
      "m", 
      "P", 
      "g", 
      "R", 
      "S"
    ], 
    "samvadi": "S", 
    "thaat": "Kafi", 
    "time": "Afternoon, 12-3", 
    "vadi": "P"
  }, 
  "HemaKalyan": {
    "aaroha": [
      "P", 
      "'D", 
      "'P", 
      "S", 
      "R", 
      "S", 
      "G", 
      "m", 
      "P", 
      "D", 
      "P", 
      "S'"
    ], 
    "avaroha": [
      "S", 
      "D", 
      "P", 
      "G", 
      "m", 
      "P", 
      "G", 
      "m", 
      "R", 
      "S"
    ], 
    "jati": "Shadav-Shadav", 
    "pakad": [
      "P", 
      "D", 
      "P", 
      "S", 
      "R", 
      "S"
    ], 
    "samvadi": "P", 
    "thaat": "Bilaval", 
    "time": "Night, 6-9", 
    "vadi": "S"
  }, 
  "Hindol": {
    "aaroha": [
      "S", 
      "G", 
      "M", 
      "D", 
      "N", 
      "D", 
      "S'"
    ], 
    "avaroha": [
      "S'", 
      "N", 
      "D", 
      "M", 
      "G", 
      "S"
    ], 
    "jati": "Audav-Audav", 
    "pakad": [
      "S", 
      "G", 
      "M", 
      "N", 
      "D", 
      "M", 
      "G", 
      "S"
    ], 
    "samvadi": "G", 
    "thaat": "Kalyaan", 
    "time": "Early Morning, 3-6", 
    "vadi": "D"
  }, 
  "Jaijaivanti": {
    "aaroha": [
      "N", 
      "S", 
      "R", 
      "G", 
      "m", 
      "P", 
      "N", 
      "S'"
    ], 
    "avaroha": [
      "S'", 
      "n", 
      "D", 
      "P", 
      "m", 
      "G", 
      "R", 
      "N'", 
      "S", 
      "'D", 
      "'n", 
      "R"
    ], 
    "jati": "Shadav-Sampoorna", 
    "pakad": [
      "R", 
      "G", 
      "m", 
      "P", 
      "D", 
      "G", 
      "m", 
      "R", 
      "G", 
      "'N", 
      "S", 
      "'D", 
      "'n", 
      "R"
    ], 
    "samvadi": "P", 
    "thaat": "Khamaj", 
    "time": "Evening, 6-9", 
    "vadi": "R"
  }, 
  "Jaikauns": {
    "aaroha": [
      "N", 
      "S", 
      "g", 
      "m", 
      "M", 
      "m", 
      "D", 
      "N", 
      "S'"
    ], 
    "avaroha": [
      "S'", 
      "N", 
      "D", 
      "m", 
      "M", 
      "m", 
      "g", 
      "S"
    ], 
    "jati": "Audav-Audav", 
    "pakad": [
      "N/A"
    ], 
    "samvadi": "S", 
    "thaat": "Kafi", 
    "time": "Night, 9-12", 
    "vadi": "m"
  }, 
  "Jaimini kalyan": {
    "aaroha": [
      "N", 
      "R", 
      "G", 
      "M", 
      "D", 
      "N", 
      "S'"
    ], 
    "avaroha": [
      "S'", 
      "N", 
      "D", 
      "P", 
      "M", 
      "G", 
      "m", 
      "G", 
      "R", 
      "S"
    ], 
    "jati": "Shadav-Sampoorna", 
    "pakad": [
      "'N", 
      "'D", 
      "'N", 
      "R", 
      "G", 
      "G", 
      "m", 
      "G", 
      "R", 
      "'N", 
      "G", 
      "R", 
      "S"
    ], 
    "samvadi": "N", 
    "thaat": "Kalyaan", 
    "time": "Evening, 6-9", 
    "vadi": "G"
  }, 
  "Jaithkalyan": {
    "aaroha": [
      "S", 
      "G", 
      "P", 
      "P", 
      "D", 
      "P", 
      "P", 
      "S'"
    ], 
    "avaroha": [
      "S'", 
      "P", 
      "P", 
      "D", 
      "P", 
      "P", 
      "D", 
      "P", 
      "G", 
      "R", 
      "S"
    ], 
    "jati": "Audav-Audav", 
    "pakad": [
      "S", 
      "G", 
      "P", 
      "P", 
      "D", 
      "P", 
      "P", 
      "G", 
      "P", 
      "G", 
      "S", 
      "R", 
      "S", 
      "S", 
      "P", 
      "D", 
      "P", 
      "S'", 
      "P", 
      "D", 
      "P", 
      "G", 
      "S"
    ], 
    "samvadi": "S'", 
    "thaat": "Kalyaan", 
    "time": "Evening, 6-9", 
    "vadi": "P"
  }, 
  "Jaladhar": {
    "aaroha": [
      "S", 
      "R", 
      "S", 
      "m", 
      "m", 
      "P", 
      "D", 
      "S'"
    ], 
    "avaroha": [
      "S'", 
      "D", 
      "P", 
      "m", 
      "R", 
      "S"
    ], 
    "jati": "Audav-Audav", 
    "pakad": [
      "D", 
      "P", 
      "m", 
      "R", 
      "S", 
      "m"
    ], 
    "samvadi": "S", 
    "thaat": "Bilaval", 
    "time": "After sunset, 6-9", 
    "vadi": "m"
  }, 
  "Janasamohini": {
    "aaroha": [
      "S", 
      "R", 
      "G", 
      "P", 
      "D", 
      "n", 
      "S'"
    ], 
    "avaroha": [
      "S'", 
      "n", 
      "D", 
      "P", 
      "G", 
      "P", 
      "G", 
      "R", 
      "S", 
      "'n", 
      "'D", 
      "S"
    ], 
    "jati": "Shadav-Shadav", 
    "pakad": [
      "P", 
      "D", 
      "n", 
      "D", 
      "P", 
      "G", 
      "R", 
      "S", 
      "'n", 
      "'D", 
      "S"
    ], 
    "samvadi": "P", 
    "thaat": "Khamaj", 
    "time": "Night, 6-9", 
    "vadi": "S"
  }, 
  "Jaunpuri": {
    "aaroha": [
      "S", 
      "R", 
      "m", 
      "P", 
      "d", 
      "n", 
      "S'"
    ], 
    "avaroha": [
      "S'", 
      "n", 
      "d", 
      "P", 
      "m", 
      "g", 
      "R", 
      "s"
    ], 
    "jati": "Shadav-Sampoorna", 
    "pakad": [
      "m", 
      "P", 
      "d", 
      "n", 
      "S", 
      "n", 
      "d", 
      "P", 
      "m", 
      "P", 
      "g", 
      "R", 
      "m", 
      "P", 
      "d", 
      "P"
    ], 
    "samvadi": "g", 
    "thaat": "Asavari", 
    "time": "Late Morning, 9-12", 
    "vadi": "d"
  }, 
  "Jhinjoti": {
    "aaroha": [
      "S", 
      "R", 
      "m", 
      "P", 
      "D", 
      "S'"
    ], 
    "avaroha": [
      "S'", 
      "n", 
      "D", 
      "P", 
      "m", 
      "G", 
      "R", 
      "G", 
      "R", 
      "R", 
      "S"
    ], 
    "jati": "Audav-Sampurna", 
    "pakad": [
      "D", 
      "S", 
      "R", 
      "m", 
      "G", 
      "P", 
      "m", 
      "G", 
      "R", 
      "S", 
      "'n", 
      "'D", 
      "'P"
    ], 
    "samvadi": "N", 
    "thaat": "Khamaj", 
    "time": "Night, 9-12", 
    "vadi": "G"
  }, 
  "Jog": {
    "aaroha": [
      "S", 
      "G", 
      "m", 
      "P", 
      "N", 
      "S'"
    ], 
    "avaroha": [
      "S'", 
      "n", 
      "P", 
      "m", 
      "G", 
      "m", 
      "g", 
      "S", 
      "g", 
      "S"
    ], 
    "jati": "Audav-Audav", 
    "pakad": [
      "S", 
      "G", 
      "G", 
      "m", 
      "S", 
      "g", 
      "'n", 
      "g", 
      "S"
    ], 
    "samvadi": "S", 
    "thaat": "Kafi", 
    "time": "Late Night, 12-3", 
    "vadi": "m"
  }, 
  "Jogiya": {
    "aaroha": [
      "S", 
      "r", 
      "m", 
      "P", 
      "d", 
      "S'"
    ], 
    "avaroha": [
      "S'", 
      "N", 
      "d", 
      "P", 
      "d", 
      "m", 
      "G", 
      "r", 
      "S"
    ], 
    "jati": "Audav-Sampurna", 
    "pakad": [
      "m", 
      "P", 
      "d", 
      "r'", 
      "S'", 
      "N", 
      "d", 
      "P", 
      "m", 
      "G", 
      "r", 
      "S"
    ], 
    "samvadi": "S", 
    "thaat": "Bhairav", 
    "time": "At daybreak, 6-9", 
    "vadi": "m"
  }, 
  "Kafi": {
    "aaroha": [
      "S", 
      "R", 
      "g", 
      "m", 
      "P", 
      "D", 
      "n", 
      "S'"
    ], 
    "avaroha": [
      "S'", 
      "n", 
      "D", 
      "P", 
      "m", 
      "g", 
      "R", 
      "S"
    ], 
    "jati": "Sampurna-Sampurna", 
    "pakad": [
      "S", 
      "R", 
      "R", 
      "g", 
      "m", 
      "P", 
      "m", 
      "P", 
      "m", 
      "P", 
      "m", 
      "P", 
      "g", 
      "R"
    ], 
    "samvadi": "R", 
    "thaat": "Kafi", 
    "time": "Night, 6-9", 
    "vadi": "P"
  }, 
  "Kalingda": {
    "aaroha": [
      "S", 
      "r", 
      "G", 
      "m", 
      "P", 
      "d", 
      "P", 
      "d", 
      "N", 
      "S'"
    ], 
    "avaroha": [
      "S'", 
      "N", 
      "d", 
      "P", 
      "m", 
      "G", 
      "r", 
      "S"
    ], 
    "jati": "Sampurna-Sampurna", 
    "pakad": [
      "P", 
      "d", 
      "P", 
      "m", 
      "G", 
      "r", 
      "S'", 
      "N", 
      "S", 
      "r", 
      "G", 
      "m", 
      "G", 
      "r", 
      "G", 
      "r", 
      "S"
    ], 
    "samvadi": "S", 
    "thaat": "Bhairav", 
    "time": "Early Morning, 3-6", 
    "vadi": "P"
  }, 
  "Kamod": {
    "aaroha": [
      "S", 
      "R", 
      "P", 
      "m", 
      "P", 
      "D", 
      "P", 
      "N", 
      "D", 
      "S"
    ], 
    "avaroha": [
      "S'", 
      "N", 
      "D", 
      "P", 
      "M", 
      "P", 
      "D", 
      "P", 
      "G", 
      "m", 
      "P", 
      "G", 
      "m", 
      "R", 
      "S"
    ], 
    "jati": "Shadav-Sampoorna", 
    "pakad": [
      "S", 
      "R", 
      "P", 
      "g", 
      "m", 
      "P", 
      "g", 
      "m", 
      "R", 
      "S"
    ], 
    "samvadi": "R", 
    "thaat": "Kalyaan", 
    "time": "Night, 6-9", 
    "vadi": "P"
  }, 
  "Kaunsi Kanada": {
    "aaroha": [
      "N", 
      "S", 
      "m", 
      "g", 
      "m", 
      "d", 
      "n", 
      "S'"
    ], 
    "avaroha": [
      "S'", 
      "n", 
      "d", 
      "m", 
      "P", 
      "m", 
      "g", 
      "R", 
      "g", 
      "m", 
      "R", 
      "S"
    ], 
    "jati": "Audav-Sampurna", 
    "pakad": [
      "N/A"
    ], 
    "samvadi": "S", 
    "thaat": "Bhairavi", 
    "time": "Around Midnight, 12-3", 
    "vadi": "m"
  }, 
  "Kedar": {
    "aaroha": [
      "S", 
      "m", 
      "m", 
      "P", 
      "M", 
      "P", 
      "D", 
      "N", 
      "S'"
    ], 
    "avaroha": [
      "S'", 
      "N", 
      "D", 
      "P", 
      "M", 
      "P", 
      "D", 
      "n", 
      "D", 
      "P", 
      "M", 
      "P", 
      "D", 
      "P", 
      "m", 
      "P", 
      "m", 
      "R", 
      "S"
    ], 
    "jati": "Audav-Shadav", 
    "pakad": [
      "M", 
      "P", 
      "D", 
      "P", 
      "m", 
      "P", 
      "m", 
      "S", 
      "R", 
      "S"
    ], 
    "samvadi": "S", 
    "thaat": "Kalyaan", 
    "time": "Early Night, 9-12", 
    "vadi": "m"
  }, 
  "Khamaj": {
    "aaroha": [
      "S", 
      "G", 
      "m", 
      "P", 
      "D", 
      "N", 
      "S'"
    ], 
    "avaroha": [
      "S'", 
      "n", 
      "D", 
      "P", 
      "m", 
      "G", 
      "R", 
      "S"
    ], 
    "jati": "Shadav-Sampoorna", 
    "pakad": [
      "G", 
      "m", 
      "n", 
      "D", 
      "P", 
      "D", 
      "m", 
      "G", 
      "P"
    ], 
    "samvadi": "N", 
    "thaat": "Khamaj", 
    "time": "Evening, 6-9", 
    "vadi": "G"
  }, 
  "Khambavati": {
    "aaroha": [
      "S", 
      "R", 
      "m", 
      "P", 
      "D", 
      "S'"
    ], 
    "avaroha": [
      "S", 
      "n", 
      "D", 
      "P", 
      "D", 
      "m", 
      "G", 
      "S"
    ], 
    "jati": "Shadav-Sampoorna", 
    "pakad": [
      "n", 
      "D", 
      "P", 
      "D", 
      "P", 
      "m", 
      "P", 
      "G", 
      "S"
    ], 
    "samvadi": "P", 
    "thaat": "Khamaj", 
    "time": "Early Night, 9-12", 
    "vadi": "S"
  }, 
  "Khat": {
    "aaroha": [
      "R", 
      "'n", 
      "S", 
      "g", 
      "m", 
      "P", 
      "d", 
      "n", 
      "S'"
    ], 
    "avaroha": [
      "R'", 
      "S'", 
      "n", 
      "D", 
      "P", 
      "m", 
      "P", 
      "g", 
      "m", 
      "R", 
      "S"
    ], 
    "jati": "Sampurna-Sampurna", 
    "pakad": [
      "R", 
      "'n", 
      "S", 
      "g", 
      "m", 
      "P", 
      "d", 
      "D", 
      "n", 
      "P", 
      "S'", 
      "n", 
      "D", 
      "P"
    ], 
    "samvadi": "S", 
    "thaat": "Asavari", 
    "time": "Late Morning, 9-12", 
    "vadi": "P"
  }, 
  "Kirvani": {
    "aaroha": [
      "S", 
      "R", 
      "g", 
      "m", 
      "P", 
      "d", 
      "N", 
      "S'"
    ], 
    "avaroha": [
      "S'", 
      "N", 
      "d", 
      "P", 
      "m", 
      "g", 
      "R", 
      "S"
    ], 
    "jati": "Sampurna-Sampurna", 
    "pakad": [
      "N/A"
    ], 
    "samvadi": "S", 
    "thaat": "", 
    "time": "Anytime in monsoon", 
    "vadi": "P"
  }, 
  "Kukubh": {
    "aaroha": [
      "S", 
      "R", 
      "G", 
      "P", 
      "D", 
      "N", 
      "S'"
    ], 
    "avaroha": [
      "S'", 
      "N", 
      "D", 
      "n", 
      "D", 
      "P", 
      "m", 
      "G", 
      "R", 
      "S", 
      "S", 
      "R", 
      "S"
    ], 
    "jati": "Shadav-Sampoorna", 
    "pakad": [
      "G", 
      "R", 
      "G", 
      "P", 
      "m", 
      "G", 
      "m", 
      "R", 
      "S", 
      "S", 
      "R"
    ], 
    "samvadi": "P", 
    "thaat": "Khamaj", 
    "time": "Early Morning, 3-6", 
    "vadi": "S"
  }, 
  "Lachchha": {
    "aaroha": [
      "S", 
      "G", 
      "R", 
      "G", 
      "P", 
      "m", 
      "P", 
      "D", 
      "N", 
      "S'"
    ], 
    "avaroha": [
      "S'", 
      "D", 
      "n", 
      "P", 
      "m", 
      "G", 
      "P", 
      "m", 
      "G", 
      "R", 
      "S"
    ], 
    "jati": "Shadav-Sampoorna", 
    "pakad": [
      "P", 
      "m", 
      "G", 
      "m", 
      "m", 
      "n", 
      "D", 
      "P", 
      "m", 
      "G", 
      "m", 
      "R", 
      "S"
    ], 
    "samvadi": "S", 
    "thaat": "Bilaval", 
    "time": "Morning, 6-9", 
    "vadi": "m"
  }, 
  "Lalit": {
    "aaroha": [
      "N", 
      "r", 
      "G", 
      "m", 
      "M", 
      "m", 
      "G", 
      "M", 
      "d", 
      "N", 
      "S'"
    ], 
    "avaroha": [
      "S'", 
      "N", 
      "d", 
      "M", 
      "m", 
      "G", 
      "r", 
      "S"
    ], 
    "jati": "Shadav-Shadav", 
    "pakad": [
      "'N", 
      "r", 
      "G", 
      "m", 
      "d", 
      "m", 
      "d", 
      "M", 
      "m", 
      "G", 
      "M", 
      "G", 
      "r", 
      "S"
    ], 
    "samvadi": "S'", 
    "thaat": "Poorvi", 
    "time": "Before Sunrise, 3-6", 
    "vadi": "m"
  }, 
  "Lalitapancham": {
    "aaroha": [
      "N", 
      "r", 
      "G", 
      "m", 
      "M", 
      "G", 
      "M", 
      "D", 
      "N", 
      "S'"
    ], 
    "avaroha": [
      "S'", 
      "N", 
      "D", 
      "N", 
      "D", 
      "P", 
      "D", 
      "M", 
      "d", 
      "M", 
      "m", 
      "G", 
      "M", 
      "G", 
      "r", 
      "S"
    ], 
    "jati": "Shadav-Sampoorna", 
    "pakad": [
      "M", 
      "D", 
      "N", 
      "D", 
      "P", 
      "D", 
      "M", 
      "m", 
      "G", 
      "M", 
      "G", 
      "r", 
      "S"
    ], 
    "samvadi": "S", 
    "thaat": "Marva", 
    "time": "Morning, 6-9", 
    "vadi": "m"
  }, 
  "Lalitpancham": {
    "aaroha": [
      "N", 
      "r", 
      "G", 
      "m", 
      "M", 
      "G", 
      "M", 
      "D", 
      "N", 
      "S'"
    ], 
    "avaroha": [
      "S'", 
      "N", 
      "D", 
      "N", 
      "D", 
      "P", 
      "D", 
      "M", 
      "d", 
      "M", 
      "m", 
      "G", 
      "M", 
      "G", 
      "r", 
      "S"
    ], 
    "jati": "Shadav-Sampoorna", 
    "pakad": [
      "M", 
      "D", 
      "N", 
      "D", 
      "P", 
      "D", 
      "M", 
      "m", 
      "G", 
      "M", 
      "r", 
      "S"
    ], 
    "samvadi": "S", 
    "thaat": "Marva", 
    "time": "Morning, 6-9", 
    "vadi": "m"
  }, 
  "Lankadahansaarang": {
    "aaroha": [
      "S", 
      "R", 
      "m", 
      "P", 
      "n", 
      "P", 
      "N", 
      "S'"
    ], 
    "avaroha": [
      "S'", 
      "D", 
      "n", 
      "P", 
      "m", 
      "P", 
      "g", 
      "g", 
      "m", 
      "R", 
      "S"
    ], 
    "jati": "Audav-Sampurna", 
    "pakad": [
      "S'", 
      "D", 
      "n", 
      "P", 
      "g", 
      "m", 
      "R", 
      "S"
    ], 
    "samvadi": "P", 
    "thaat": "Kafi", 
    "time": "Afternoon, 12-3", 
    "vadi": "R"
  }, 
  "Maand": {
    "aaroha": [
      "S", 
      "G", 
      "m", 
      "P", 
      "D", 
      "N", 
      "S'"
    ], 
    "avaroha": [
      "S'", 
      "N", 
      "D", 
      "P", 
      "D", 
      "P", 
      "N", 
      "D", 
      "P", 
      "G", 
      "m", 
      "G", 
      "R", 
      "S"
    ], 
    "jati": "Shadav-Sampoorna", 
    "pakad": [
      "G", 
      "m", 
      "P", 
      "D", 
      "N", 
      "S'"
    ], 
    "samvadi": "P", 
    "thaat": "Bilaval", 
    "time": "Evening, 6-9", 
    "vadi": "S"
  }, 
  "Madhmad Sarang": {
    "aaroha": [
      "S", 
      "R", 
      "m", 
      "P", 
      "n", 
      "S'"
    ], 
    "avaroha": [
      "S'", 
      "n", 
      "P", 
      "m", 
      "R", 
      "R", 
      "'n", 
      "S"
    ], 
    "jati": "Audav-Audav", 
    "pakad": [
      "'n", 
      "S", 
      "R", 
      "P", 
      "m", 
      "R", 
      "'n", 
      "R", 
      "S", 
      "m", 
      "P", 
      "n", 
      "P", 
      "m", 
      "R", 
      "m", 
      "R", 
      "S'", 
      "n", 
      "S"
    ], 
    "samvadi": "P", 
    "thaat": "Kafi", 
    "time": "Early Afternoon, 12-3", 
    "vadi": "R"
  }, 
  "Madhmadi saarang": {
    "aaroha": [
      "S", 
      "R", 
      "m", 
      "P", 
      "n", 
      "S'"
    ], 
    "avaroha": [
      "S'", 
      "n", 
      "P", 
      "m", 
      "R", 
      "R", 
      "'n", 
      "S"
    ], 
    "jati": "Audav-Audav", 
    "pakad": [
      "'n", 
      "S", 
      "R", 
      "P", 
      "m", 
      "R", 
      "'n", 
      "R", 
      "S", 
      "m", 
      "P", 
      "n", 
      "P", 
      "m", 
      "R", 
      "m", 
      "R", 
      "S'", 
      "n", 
      "S"
    ], 
    "samvadi": "P", 
    "thaat": "Kafi", 
    "time": "Late Morning, 9-12", 
    "vadi": "R"
  }, 
  "Madhuvanti": {
    "aaroha": [
      "N", 
      "S", 
      "g", 
      "M", 
      "P", 
      "N", 
      "S'"
    ], 
    "avaroha": [
      "S'", 
      "N", 
      "D", 
      "P", 
      "M", 
      "P", 
      "D", 
      "n", 
      "D", 
      "P", 
      "M", 
      "g", 
      "R", 
      "S"
    ], 
    "jati": "Audav-Sampurna", 
    "pakad": [
      "D", 
      "M", 
      "P", 
      "g", 
      "M", 
      "g", 
      "R", 
      "S"
    ], 
    "samvadi": "S", 
    "thaat": "Todi", 
    "time": "Afternoon, 12-3", 
    "vadi": "P"
  }, 
  "Malashri": {
    "aaroha": [
      "S", 
      "G", 
      "P", 
      "N", 
      "S"
    ], 
    "avaroha": [
      "S", 
      "P", 
      "M", 
      "P", 
      "G", 
      "S"
    ], 
    "jati": "Audav-Audav", 
    "pakad": [
      "S", 
      "P", 
      "M", 
      "P", 
      "G", 
      "S"
    ], 
    "samvadi": "S", 
    "thaat": "Kalyaan", 
    "time": "Evening, 6-9", 
    "vadi": "P"
  }, 
  "Malav": {
    "aaroha": [
      "S", 
      "G", 
      "m", 
      "d", 
      "n", 
      "S'"
    ], 
    "avaroha": [
      "S'", 
      "n", 
      "d", 
      "P", 
      "D", 
      "D", 
      "n", 
      "D", 
      "P", 
      "m", 
      "G", 
      "m", 
      "G", 
      "m", 
      "g", 
      "g", 
      "S"
    ], 
    "jati": "Audav-Shadav", 
    "pakad": [
      "S'", 
      "n", 
      "d", 
      "P", 
      "D", 
      "D", 
      "n", 
      "D", 
      "P", 
      "m", 
      "G", 
      "m", 
      "g", 
      "S"
    ], 
    "samvadi": "S", 
    "thaat": "Bhairavi", 
    "time": "Late Night, 12-3", 
    "vadi": "m"
  }, 
  "Malgunj": {
    "aaroha": [
      "S", 
      "R", 
      "G", 
      "m", 
      "D", 
      "N", 
      "S'"
    ], 
    "avaroha": [
      "S'", 
      "n", 
      "D", 
      "P", 
      "m", 
      "G", 
      "m", 
      "g", 
      "R", 
      "S"
    ], 
    "jati": "Shadav-Sampoorna", 
    "pakad": [
      "G", 
      "m", 
      "g", 
      "R", 
      "S", 
      "'N", 
      "S", 
      "'D", 
      "'n", 
      "S", 
      "G", 
      "m"
    ], 
    "samvadi": "S", 
    "thaat": "Kafi", 
    "time": "Late Morning, 9-12", 
    "vadi": "m"
  }, 
  "Maligaura": {
    "aaroha": [
      "S", 
      "r", 
      "'N", 
      "'d", 
      "'N", 
      "r", 
      "G", 
      "M", 
      "G", 
      "M", 
      "P", 
      "N", 
      "S'"
    ], 
    "avaroha": [
      "S'", 
      "r'", 
      "N", 
      "d", 
      "P", 
      "N", 
      "M", 
      "G", 
      "M", 
      "'N", 
      "r", 
      "S"
    ], 
    "jati": "Shadav-Sampoorna", 
    "pakad": [
      "S", 
      "r", 
      "'N", 
      "'d", 
      "'N", 
      "P", 
      "d", 
      "M", 
      "G", 
      "M", 
      "G", 
      "r", 
      "G"
    ], 
    "samvadi": "P", 
    "thaat": "Poorvi", 
    "time": "Evening, 6-9", 
    "vadi": "S"
  }, 
  "Malkauns": {
    "aaroha": [
      "S", 
      "g", 
      "m", 
      "d", 
      "n", 
      "S'"
    ], 
    "avaroha": [
      "S'", 
      "n", 
      "d", 
      "m", 
      "g", 
      "S"
    ], 
    "jati": "Audav-Audav", 
    "pakad": [
      "'d", 
      "n", 
      "S", 
      "m", 
      "g", 
      "m", 
      "d", 
      "g", 
      "m", 
      "g", 
      "'n", 
      "S"
    ], 
    "samvadi": "S", 
    "thaat": "Bhairavi", 
    "time": "Late Night, 12-3", 
    "vadi": "m"
  }, 
  "Maluha": {
    "aaroha": [
      "R", 
      "'N", 
      "S", 
      "m", 
      "R", 
      "S", 
      "m", 
      "G", 
      "P", 
      "M", 
      "D", 
      "M", 
      "P", 
      "S'"
    ], 
    "avaroha": [
      "S'", 
      "N", 
      "D", 
      "M", 
      "P", 
      "G", 
      "P", 
      "G", 
      "m", 
      "R", 
      "S", 
      "'n", 
      "'D", 
      "'P", 
      "'m", 
      "'P", 
      "S"
    ], 
    "jati": "Shadav-Shadav", 
    "pakad": [
      "m", 
      "R", 
      "S", 
      "S", 
      "'d", 
      "'P", 
      "'m", 
      "'P", 
      "'P", 
      "'N", 
      "'N", 
      "S"
    ], 
    "samvadi": "S", 
    "thaat": "Kalyaan", 
    "time": "Evening, 6-9", 
    "vadi": "m"
  }, 
  "Malwi": {
    "aaroha": [
      "S", 
      "G", 
      "P", 
      "M", 
      "d", 
      "S'"
    ], 
    "avaroha": [
      "S'", 
      "N", 
      "P", 
      "M", 
      "G", 
      "r", 
      "S"
    ], 
    "jati": "Shadav-Sampoorna", 
    "pakad": [
      "G", 
      "P", 
      "M", 
      "d", 
      "S'", 
      "N", 
      "P", 
      "G", 
      "M", 
      "G", 
      "r", 
      "S"
    ], 
    "samvadi": "P", 
    "thaat": "Poorvi", 
    "time": "Evening, 6-9", 
    "vadi": "S"
  }, 
  "Manohari amba": {
    "aaroha": [
      "S", 
      "R", 
      "g", 
      "m", 
      "D", 
      "N", 
      "S'"
    ], 
    "avaroha": [
      "S'", 
      "N", 
      "D", 
      "m", 
      "g", 
      "R", 
      "S"
    ], 
    "jati": "Shadav-Shadav", 
    "pakad": [
      "m", 
      "g", 
      "R", 
      "'N", 
      "S", 
      "'D", 
      "'N", 
      "S"
    ], 
    "samvadi": "S", 
    "thaat": "Kafi", 
    "time": "Morning, 9-12", 
    "vadi": "m"
  }, 
  "Marg Bihag": {
    "aaroha": [
      "N", 
      "S", 
      "G", 
      "M", 
      "P", 
      "N", 
      "S'"
    ], 
    "avaroha": [
      "S", 
      "'N", 
      "D", 
      "P", 
      "M", 
      "G", 
      "R", 
      "S"
    ], 
    "jati": "Audav-Sampurna", 
    "pakad": [
      "G", 
      "M", 
      "P", 
      "N", 
      "D", 
      "M", 
      "G", 
      "M", 
      "G", 
      "R", 
      "S", 
      "R", 
      "S"
    ], 
    "samvadi": "N", 
    "thaat": "Kalyaan", 
    "time": "Early Night, 9-12", 
    "vadi": "G"
  }, 
  "Maru Bihag": {
    "aaroha": [
      "N", 
      "S", 
      "G", 
      "M", 
      "P", 
      "m", 
      "G", 
      "M", 
      "P", 
      "N", 
      "S'"
    ], 
    "avaroha": [
      "S'", 
      "N", 
      "D", 
      "P", 
      "M", 
      "G", 
      "M", 
      "G", 
      "R", 
      "S"
    ], 
    "jati": "Audav-Sampurna", 
    "pakad": [
      "P", 
      "G", 
      "M", 
      "G", 
      "R", 
      "S", 
      "S", 
      "m", 
      "G", 
      "S", 
      "G", 
      "M", 
      "P"
    ], 
    "samvadi": "N", 
    "thaat": "Kalyaan", 
    "time": "Afternoon, 3-6", 
    "vadi": "G"
  }, 
  "Marva": {
    "aaroha": [
      "N", 
      "r", 
      "G", 
      "M", 
      "D", 
      "N", 
      "D", 
      "S'"
    ], 
    "avaroha": [
      "S'", 
      "N", 
      "D", 
      "M", 
      "G", 
      "r", 
      "S"
    ], 
    "jati": "Shadav-Shadav", 
    "pakad": [
      "D", 
      "M", 
      "G", 
      "r", 
      "G", 
      "M", 
      "G", 
      "r", 
      "'N", 
      "S"
    ], 
    "samvadi": "D", 
    "thaat": "Marva", 
    "time": "At Sunset, 3-6", 
    "vadi": "r"
  }, 
  "Meeramalhaar": {
    "aaroha": [
      "S", 
      "R", 
      "P", 
      "n", 
      "D", 
      "N", 
      "S'"
    ], 
    "avaroha": [
      "S'", 
      "R'", 
      "d", 
      "d", 
      "n", 
      "P", 
      "m", 
      "P", 
      "g", 
      "g", 
      "m", 
      "R", 
      "S"
    ], 
    "jati": "Shadav-Sampoorna", 
    "pakad": [
      "P", 
      "n", 
      "D", 
      "N", 
      "S'", 
      "R'", 
      "d", 
      "d", 
      "n", 
      "P"
    ], 
    "samvadi": "P", 
    "thaat": "Asavari", 
    "time": "Any time in rainy season", 
    "vadi": "S"
  }, 
  "Megh": {
    "aaroha": [
      "S", 
      "m", 
      "R", 
      "P", 
      "m", 
      "P", 
      "n", 
      "S'"
    ], 
    "avaroha": [
      "S'", 
      "n", 
      "P", 
      "m", 
      "R", 
      "S"
    ], 
    "jati": "Audav-Audav", 
    "pakad": [
      "R", 
      "R", 
      "S", 
      "'n", 
      "S", 
      "m", 
      "R", 
      "p", 
      "m", 
      "R", 
      "n", 
      "S"
    ], 
    "samvadi": "P", 
    "thaat": "Kafi", 
    "time": "Any time in rainy season", 
    "vadi": "S"
  }, 
  "Miya ki Malhaar": {
    "aaroha": [
      "N", 
      "S", 
      "m", 
      "R", 
      "P", 
      "m", 
      "P", 
      "n", 
      "D", 
      "N", 
      "S'"
    ], 
    "avaroha": [
      "S'", 
      "N", 
      "S'", 
      "D", 
      "n", 
      "m", 
      "P", 
      "g", 
      "m", 
      "R", 
      "S"
    ], 
    "jati": "Sampurna-Shadav", 
    "pakad": [
      "R", 
      "P", 
      "g", 
      "m", 
      "R", 
      "S", 
      "'n", 
      "'", 
      "D", 
      "'N", 
      "S"
    ], 
    "samvadi": "P", 
    "thaat": "Kafi", 
    "time": "Any time in rains/midnight", 
    "vadi": "R"
  }, 
  "Mohiniahi": {
    "aaroha": [
      "S", 
      "r", 
      "G", 
      "m", 
      "P", 
      "D", 
      "n", 
      "S'"
    ], 
    "avaroha": [
      "S'", 
      "N", 
      "D", 
      "P", 
      "m", 
      "G", 
      "R", 
      "S"
    ], 
    "jati": "Sampurna-Sampurna", 
    "pakad": [
      "S", 
      "R", 
      "G", 
      "m", 
      "P", 
      "d", 
      "P", 
      "m", 
      "g", 
      "R", 
      "g", 
      "S"
    ], 
    "samvadi": "n", 
    "thaat": "Asavari", 
    "time": "Night, 9-12", 
    "vadi": "m"
  }, 
  "Multani": {
    "aaroha": [
      "N", 
      "S", 
      "g", 
      "M", 
      "P", 
      "N", 
      "S'"
    ], 
    "avaroha": [
      "S'", 
      "N", 
      "d", 
      "P", 
      "M", 
      "g", 
      "r", 
      "S"
    ], 
    "jati": "Audav-Sampurna", 
    "pakad": [
      "'N", 
      "S", 
      "M", 
      "g", 
      "M", 
      "P", 
      "g", 
      "M", 
      "g", 
      "M", 
      "g", 
      "S", 
      "N'", 
      "S", 
      "g", 
      "r", 
      "S"
    ], 
    "samvadi": "S", 
    "thaat": "Todi", 
    "time": "Afternoon, 3-6", 
    "vadi": "P"
  }, 
  "Naat": {
    "aaroha": [
      "S", 
      "R", 
      "G", 
      "m", 
      "P", 
      "D", 
      "N", 
      "S'"
    ], 
    "avaroha": [
      "S'", 
      "N", 
      "d", 
      "P", 
      "m", 
      "g", 
      "R", 
      "S"
    ], 
    "jati": "Sampurna-Sampurna", 
    "pakad": [
      "S", 
      "G", 
      "m", 
      "P", 
      "G", 
      "m", 
      "R", 
      "G", 
      "m", 
      "P", 
      "m", 
      "G", 
      "m", 
      "R", 
      "S"
    ], 
    "samvadi": "S", 
    "thaat": "Bilaval", 
    "time": "Early Night, 9-12", 
    "vadi": "m"
  }, 
  "Naat Malhar": {
    "aaroha": [
      "S", 
      "R", 
      "G", 
      "m", 
      "m", 
      "R", 
      "P", 
      "n", 
      "D", 
      "N", 
      "S'"
    ], 
    "avaroha": [
      "S'", 
      "D", 
      "n", 
      "P", 
      "m", 
      "G", 
      "R", 
      "R", 
      "G", 
      "G", 
      "m", 
      "R", 
      "S"
    ], 
    "jati": "Sampurna-Sampurna", 
    "pakad": [
      "S", 
      "R", 
      "G", 
      "m", 
      "m", 
      "R", 
      "P", 
      "D", 
      "n", 
      "P", 
      "m", 
      "P"
    ], 
    "samvadi": "S", 
    "thaat": "Khamaj", 
    "time": "Early Night, 9-12", 
    "vadi": "m"
  }, 
  "Naatbhairav": {
    "aaroha": [
      "S", 
      "R", 
      "G", 
      "m", 
      "P", 
      "d", 
      "N", 
      "S'"
    ], 
    "avaroha": [
      "S'", 
      "N", 
      "D", 
      "P", 
      "m", 
      "G", 
      "R", 
      "S"
    ], 
    "jati": "Sampurna-Sampurna", 
    "pakad": [
      "S", 
      "R", 
      "G", 
      "m", 
      "d", 
      "P", 
      "G", 
      "m", 
      "R", 
      "S", 
      "R", 
      "'N", 
      "'d", 
      "S"
    ], 
    "samvadi": "S", 
    "thaat": "Bhairav", 
    "time": "Morning, 6-9", 
    "vadi": "P"
  }, 
  "Narayani": {
    "aaroha": [
      "S", 
      "R", 
      "m", 
      "P", 
      "D", 
      "n", 
      "D", 
      "S'"
    ], 
    "avaroha": [
      "S'", 
      "n", 
      "D", 
      "P", 
      "m", 
      "R", 
      "S"
    ], 
    "jati": "Shadav-Shadav", 
    "pakad": [
      "R", 
      "m", 
      "P", 
      "n", 
      "D", 
      "P"
    ], 
    "samvadi": "S", 
    "thaat": "Khamaj", 
    "time": "Late Night, 9-12", 
    "vadi": "P"
  }, 
  "Nata bihag": {
    "aaroha": [
      "S", 
      "R", 
      "G", 
      "m", 
      "P", 
      "P", 
      "N", 
      "N", 
      "S'"
    ], 
    "avaroha": [
      "S'", 
      "N", 
      "D", 
      "P", 
      "G", 
      "m", 
      "n", 
      "D", 
      "P", 
      "m", 
      "G", 
      "m", 
      "G", 
      "R", 
      "S"
    ], 
    "jati": "Audav-Sampurna", 
    "pakad": [
      "G", 
      "m", 
      "n", 
      "D", 
      "P", 
      "P", 
      "m", 
      "G", 
      "R", 
      "G", 
      "m", 
      "P", 
      "m", 
      "G", 
      "R", 
      "S"
    ], 
    "samvadi": "S", 
    "thaat": "Khamaj", 
    "time": "Early Night, 9-12", 
    "vadi": "P"
  }, 
  "Pahadi": {
    "aaroha": [
      "P", 
      "'D", 
      "S", 
      "R", 
      "G", 
      "P", 
      "D", 
      "S'"
    ], 
    "avaroha": [
      "S'", 
      "N", 
      "D", 
      "P", 
      "m", 
      "G", 
      "R", 
      "S", 
      "'D", 
      "'P", 
      "'D", 
      "S"
    ], 
    "jati": "Audav-Sampurna", 
    "pakad": [
      "S", 
      "'D", 
      "'P", 
      "'D", 
      "'m", 
      "'G", 
      "'P", 
      "'D", 
      "'S"
    ], 
    "samvadi": "P", 
    "thaat": "Bilaval", 
    "time": "Night, 6-9", 
    "vadi": "S"
  }, 
  "Palasi": {
    "aaroha": [
      "S", 
      "g", 
      "m", 
      "P", 
      "n", 
      "S'"
    ], 
    "avaroha": [
      "S'", 
      "n", 
      "P", 
      "m", 
      "G", 
      "R", 
      "S"
    ], 
    "jati": "Audav-Audav", 
    "pakad": [
      "P", 
      "n", 
      "P", 
      "m", 
      "g", 
      "R", 
      "S"
    ], 
    "samvadi": "S'", 
    "thaat": "Kafi", 
    "time": "Afternoon, 3-6", 
    "vadi": "P"
  }, 
  "Pancham": {
    "aaroha": [
      "S", 
      "m", 
      "G", 
      "M", 
      "D", 
      "N", 
      "D", 
      "N", 
      "M", 
      "D", 
      "S'"
    ], 
    "avaroha": [
      "S'", 
      "N", 
      "D", 
      "M", 
      "D", 
      "M", 
      "G", 
      "r", 
      "s"
    ], 
    "jati": "Audav-Audav", 
    "pakad": [
      "M", 
      "D", 
      "S'", 
      "N", 
      "D", 
      "M", 
      "D", 
      "M", 
      "G", 
      "r", 
      "S", 
      "S", 
      "m", 
      "G", 
      "M", 
      "D", 
      "N", 
      "D", 
      "N", 
      "M", 
      "D"
    ], 
    "samvadi": "S", 
    "thaat": "Marva", 
    "time": "Night, 6-9", 
    "vadi": "m"
  }, 
  "Paraj": {
    "aaroha": [
      "N", 
      "S", 
      "G", 
      "M", 
      "P", 
      "d", 
      "N", 
      "S'"
    ], 
    "avaroha": [
      "S'", 
      "N", 
      "d", 
      "P", 
      "M", 
      "P", 
      "d", 
      "P", 
      "m", 
      "G", 
      "r", 
      "s"
    ], 
    "jati": "Shadav-Sampoorna", 
    "pakad": [
      "S'", 
      "N", 
      "d", 
      "P", 
      "M", 
      "P", 
      "d", 
      "P", 
      "G", 
      "m", 
      "G", 
      "M", 
      "G", 
      "r", 
      "S"
    ], 
    "samvadi": "P", 
    "thaat": "Poorvi", 
    "time": "Late Night, 12-3", 
    "vadi": "S"
  }, 
  "Patdip": {
    "aaroha": [
      "N", 
      "S", 
      "g", 
      "m", 
      "P", 
      "N", 
      "S'"
    ], 
    "avaroha": [
      "S'", 
      "N", 
      "S'", 
      "D", 
      "P", 
      "m", 
      "P", 
      "g", 
      "R", 
      "S"
    ], 
    "jati": "Audav-Sampurna", 
    "pakad": [
      "g", 
      "m", 
      "P", 
      "N", 
      "D", 
      "N", 
      "S'", 
      "D", 
      "P", 
      "m", 
      "P", 
      "g"
    ], 
    "samvadi": "S", 
    "thaat": "Kafi", 
    "time": "Afternoon, 3-6", 
    "vadi": "P"
  }, 
  "Pilu": {
    "aaroha": [
      "N", 
      "S", 
      "R", 
      "m", 
      "P", 
      "N", 
      "S'"
    ], 
    "avaroha": [
      "S'", 
      "n", 
      "D", 
      "P", 
      "m", 
      "P", 
      "d", 
      "P", 
      "m", 
      "G", 
      "m", 
      "P", 
      "g", 
      "R", 
      "S", 
      "'N", 
      "S", 
      "g", 
      "r", 
      "S"
    ], 
    "jati": "Mishra/Sankeerna", 
    "pakad": [
      "G", 
      "m", 
      "P", 
      "g", 
      "R", 
      "S'", 
      "N", 
      "S"
    ], 
    "samvadi": "S", 
    "thaat": "Kafi", 
    "time": "Afternoon, 3-6", 
    "vadi": "P"
  }, 
  "Poorvi": {
    "aaroha": [
      "N", 
      "r", 
      "G", 
      "M", 
      "d", 
      "N", 
      "S'"
    ], 
    "avaroha": [
      "S'", 
      "N", 
      "d", 
      "P", 
      "M", 
      "G", 
      "m", 
      "r", 
      "G", 
      "M", 
      "G", 
      "r", 
      "S"
    ], 
    "jati": "Shadav-Sampoorna", 
    "pakad": [
      "P", 
      "d", 
      "P", 
      "M", 
      "G", 
      "m", 
      "r", 
      "G", 
      "M", 
      "G", 
      "r", 
      "S"
    ], 
    "samvadi": "N", 
    "thaat": "Poorvi", 
    "time": "Sunset, 3-6", 
    "vadi": "G"
  }, 
  "Prabhat": {
    "aaroha": [
      "S", 
      "r", 
      "G", 
      "m", 
      "M", 
      "G", 
      "G", 
      "m", 
      "P", 
      "d", 
      "N", 
      "S'"
    ], 
    "avaroha": [
      "S'", 
      "N", 
      "d", 
      "P", 
      "m", 
      "m", 
      "d", 
      "M", 
      "m", 
      "G", 
      "r", 
      "G", 
      "M", 
      "G", 
      "r", 
      "S"
    ], 
    "jati": "Sampurna-Sampurna", 
    "pakad": [
      "G", 
      "m", 
      "d", 
      "d", 
      "P", 
      "G", 
      "m", 
      "M", 
      "d", 
      "M", 
      "m", 
      "G", 
      "m"
    ], 
    "samvadi": "S", 
    "thaat": "Bhairav", 
    "time": "Morning, 6-9", 
    "vadi": "m"
  }, 
  "Pradeepaki": {
    "aaroha": [
      "S", 
      "G", 
      "m", 
      "P", 
      "N", 
      "S'"
    ], 
    "avaroha": [
      "S'", 
      "n", 
      "D", 
      "P", 
      "m", 
      "g", 
      "R", 
      "S"
    ], 
    "jati": "Audav-Sampurna", 
    "pakad": [
      "G", 
      "m", 
      "P", 
      "g", 
      "m", 
      "g", 
      "R", 
      "S"
    ], 
    "samvadi": "S", 
    "thaat": "Kafi", 
    "time": "Afternoon, 12-3", 
    "vadi": "m"
  }, 
  "Purba": {
    "aaroha": [
      "N", 
      "r", 
      "G", 
      "M", 
      "D", 
      "N", 
      "S'"
    ], 
    "avaroha": [
      "S'", 
      "N", 
      "D", 
      "P", 
      "M", 
      "G", 
      "r", 
      "G", 
      "r", 
      "S"
    ], 
    "jati": "Sampurna-Sampurna", 
    "pakad": [
      "N", 
      "D", 
      "P", 
      "M", 
      "G", 
      "M", 
      "D", 
      "M", 
      "G", 
      "r", 
      "S"
    ], 
    "samvadi": "P", 
    "thaat": "Marva", 
    "time": "Late Evening , 3-6", 
    "vadi": "S"
  }, 
  "Puriya": {
    "aaroha": [
      "N", 
      "r", 
      "G", 
      "M", 
      "D", 
      "N", 
      "r'", 
      "S'"
    ], 
    "avaroha": [
      "r'", 
      "N", 
      "D", 
      "M", 
      "G", 
      "M", 
      "G", 
      "r", 
      "S"
    ], 
    "jati": "Shadav-Shadav", 
    "pakad": [
      "G", 
      "N", 
      "r'", 
      "S", 
      "M", 
      "G", 
      "r", 
      "G", 
      "'N", 
      "r", 
      "S"
    ], 
    "samvadi": "N", 
    "thaat": "Marva", 
    "time": "Just after sunset, 3-6", 
    "vadi": "G"
  }, 
  "Puriyadhanashri": {
    "aaroha": [
      "N", 
      "r", 
      "G", 
      "M", 
      "d", 
      "N", 
      "S'"
    ], 
    "avaroha": [
      "S'", 
      "N", 
      "r'", 
      "N", 
      "d", 
      "P", 
      "M", 
      "G", 
      "M", 
      "r", 
      "G", 
      "r", 
      "S"
    ], 
    "jati": "Audav-Sampurna", 
    "pakad": [
      "'N", 
      "r", 
      "M", 
      "G", 
      "P", 
      "M", 
      "d", 
      "N", 
      "d", 
      "P", 
      "M", 
      "G", 
      "M", 
      "r", 
      "G", 
      "r", 
      "S"
    ], 
    "samvadi": "S", 
    "thaat": "Poorvi", 
    "time": "After sunset, 3-6", 
    "vadi": "P"
  }, 
  "Purva Kalyaan": {
    "aaroha": [
      "N", 
      "r", 
      "G", 
      "M", 
      "D", 
      "N", 
      "S'"
    ], 
    "avaroha": [
      "S'", 
      "N", 
      "D", 
      "P", 
      "M", 
      "G", 
      "r", 
      "G", 
      "r", 
      "S"
    ], 
    "jati": "Sampurna-Sampurna", 
    "pakad": [
      "N", 
      "D", 
      "P", 
      "M", 
      "G", 
      "M", 
      "D", 
      "M", 
      "G", 
      "r", 
      "S"
    ], 
    "samvadi": "P", 
    "thaat": "Marva", 
    "time": "Evening, 6-9", 
    "vadi": "S"
  }, 
  "Rageshri": {
    "aaroha": [
      "n", 
      "S", 
      "G", 
      "M", 
      "D", 
      "n", 
      "S'"
    ], 
    "avaroha": [
      "S'", 
      "n", 
      "D", 
      "m", 
      "G", 
      "m", 
      "R", 
      "S"
    ], 
    "jati": "Audav-Shadav", 
    "pakad": [
      "'D", 
      "'n", 
      "S", 
      "G", 
      "m", 
      "G", 
      "m", 
      "R", 
      "S"
    ], 
    "samvadi": "S", 
    "thaat": "Khamaj", 
    "time": "Late Night, 12-3", 
    "vadi": "m"
  }, 
  "Ram Priya": {
    "aaroha": [
      "S", 
      "r", 
      "G", 
      "m", 
      "P", 
      "n", 
      "S'"
    ], 
    "avaroha": [
      "S'", 
      "n", 
      "P", 
      "m", 
      "G", 
      "m", 
      "g", 
      "r", 
      "S"
    ], 
    "jati": "Shadav-Shadav", 
    "pakad": [
      "P", 
      "n", 
      "P", 
      "m", 
      "G", 
      "m", 
      "g", 
      "r", 
      "g", 
      "r", 
      "S"
    ], 
    "samvadi": "S", 
    "thaat": "Todi", 
    "time": "Morning, 9-12", 
    "vadi": "m"
  }, 
  "Ramkali": {
    "aaroha": [
      "S", 
      "r", 
      "G", 
      "m", 
      "P", 
      "G", 
      "m", 
      "d", 
      "N", 
      "S'"
    ], 
    "avaroha": [
      "S'", 
      "N", 
      "d", 
      "P", 
      "M", 
      "P", 
      "d", 
      "d", 
      "P", 
      "G", 
      "m", 
      "r", 
      "S"
    ], 
    "jati": "Sampurna-Sampurna", 
    "pakad": [
      "M", 
      "P", 
      "d", 
      "n", 
      "d", 
      "P", 
      "G", 
      "m", 
      "R", 
      "S", 
      "G", 
      "m", 
      "P"
    ], 
    "samvadi": "S", 
    "thaat": "Bhairav", 
    "time": "At daybreak, 6-9", 
    "vadi": "P"
  }, 
  "Reva": {
    "aaroha": [
      "S", 
      "r", 
      "G", 
      "P", 
      "d", 
      "P", 
      "S'"
    ], 
    "avaroha": [
      "S'", 
      "d", 
      "P", 
      "G", 
      "r", 
      "S"
    ], 
    "jati": "Audav-Audav", 
    "pakad": [
      "S", 
      "r", 
      "g", 
      "P", 
      "d", 
      "P", 
      "G", 
      "S", 
      "r", 
      "G", 
      "r", 
      "G"
    ], 
    "samvadi": "P", 
    "thaat": "Poorvi", 
    "time": "Evening, 6-9", 
    "vadi": "S"
  }, 
  "Saajgiro": {
    "aaroha": [
      "N", 
      "r", 
      "G", 
      "M", 
      "G", 
      "M", 
      "P", 
      "d", 
      "P", 
      "m", 
      "N", 
      "D", 
      "S'"
    ], 
    "avaroha": [
      "S'", 
      "N", 
      "r'", 
      "N", 
      "d", 
      "P", 
      "P", 
      "D", 
      "G", 
      "M", 
      "D", 
      "G", 
      "M", 
      "G", 
      "r", 
      "S"
    ], 
    "jati": "Sampurna-Sampurna", 
    "pakad": [
      "m", 
      "N", 
      "D", 
      "S'", 
      "N", 
      "r'", 
      "N", 
      "d", 
      "P", 
      "P", 
      "D", 
      "G", 
      "M", 
      "G", 
      "r", 
      "S"
    ], 
    "samvadi": "N", 
    "thaat": "Poorvi", 
    "time": "Evening, 6-9", 
    "vadi": "G"
  }, 
  "Samanthasarang": {
    "aaroha": [
      "S", 
      "R", 
      "m", 
      "P", 
      "N", 
      "S'"
    ], 
    "avaroha": [
      "S'", 
      "n", 
      "D", 
      "P", 
      "m", 
      "R", 
      "m", 
      "R", 
      "'N", 
      "S"
    ], 
    "jati": "Audav-Audav", 
    "pakad": [
      "R", 
      "M", 
      "P", 
      "n", 
      "D", 
      "P", 
      "m", 
      "R"
    ], 
    "samvadi": "P", 
    "thaat": "Khamaj", 
    "time": "Afternoon, 12-3", 
    "vadi": "R"
  }, 
  "Sarparda": {
    "aaroha": [
      "S", 
      "R", 
      "G", 
      "G", 
      "R", 
      "G", 
      "m", 
      "P", 
      "D", 
      "N", 
      "S'"
    ], 
    "avaroha": [
      "S'", 
      "N", 
      "D", 
      "P", 
      "D", 
      "n", 
      "D", 
      "P", 
      "m", 
      "G", 
      "R", 
      "G", 
      "R", 
      "S"
    ], 
    "jati": "Sampurna-Sampurna", 
    "pakad": [
      "D", 
      "n", 
      "D", 
      "P", 
      "m", 
      "G", 
      "R", 
      "G", 
      "R", 
      "S"
    ], 
    "samvadi": "P", 
    "thaat": "Bilaval", 
    "time": "Early Morning, 3-6", 
    "vadi": "S"
  }, 
  "Shahana": {
    "aaroha": [
      "R", 
      "n", 
      "S", 
      "g", 
      "m", 
      "P", 
      "n", 
      "D", 
      "n", 
      "P", 
      "m", 
      "P", 
      "n", 
      "P", 
      "S'"
    ], 
    "avaroha": [
      "S'", 
      "n", 
      "D", 
      "n", 
      "P", 
      "m", 
      "P", 
      "g", 
      "m", 
      "R", 
      "S"
    ], 
    "jati": "Sampurna-Sampurna", 
    "pakad": [
      "n", 
      "D", 
      "n", 
      "P", 
      "m", 
      "P", 
      "g", 
      "m", 
      "R", 
      "S"
    ], 
    "samvadi": "S", 
    "thaat": "Kafi", 
    "time": "Late Night, 12-3", 
    "vadi": "P"
  }, 
  "Shankara": {
    "aaroha": [
      "S", 
      "G", 
      "P", 
      "N", 
      "D", 
      "S'"
    ], 
    "avaroha": [
      "S'", 
      "N", 
      "P", 
      "G", 
      "P", 
      "G", 
      "S"
    ], 
    "jati": "Audav-Shadav", 
    "pakad": [
      "S", 
      "'N", 
      "'P", 
      "'N", 
      "'D", 
      "S", 
      "G", 
      "P", 
      "G", 
      "R", 
      "S"
    ], 
    "samvadi": "N", 
    "thaat": "Bilaval", 
    "time": "Late Night, 12-3", 
    "vadi": "G"
  }, 
  "Shivabhairav": {
    "aaroha": [
      "S", 
      "r", 
      "S", 
      "G", 
      "m", 
      "P", 
      "d", 
      "d", 
      "S'"
    ], 
    "avaroha": [
      "S'", 
      "n", 
      "d", 
      "P", 
      "m", 
      "g", 
      "m", 
      "P", 
      "m", 
      "G", 
      "m", 
      "r", 
      "g", 
      "r", 
      "S"
    ], 
    "jati": "Sampurna-Sampurna", 
    "pakad": [
      "g", 
      "m", 
      "P", 
      "d", 
      "d'", 
      "S'", 
      "r'", 
      "n", 
      "d", 
      "P", 
      "d", 
      "n", 
      "d", 
      "P", 
      "m"
    ], 
    "samvadi": "S", 
    "thaat": "Bhairav", 
    "time": "Morning, 6-9", 
    "vadi": "P"
  }, 
  "Shree": {
    "aaroha": [
      "S", 
      "R", 
      "m", 
      "P", 
      "N", 
      "S'"
    ], 
    "avaroha": [
      "S'", 
      "N", 
      "r'", 
      "N", 
      "d", 
      "M", 
      "d", 
      "M", 
      "G", 
      "r", 
      "S"
    ], 
    "jati": "Audav-Sampurna", 
    "pakad": [
      "r", 
      "r", 
      "P", 
      "M", 
      "P", 
      "d", 
      "M", 
      "G", 
      "r", 
      "S", 
      "M", 
      "P", 
      "N", 
      "S'", 
      "r'", 
      "N", 
      "d", 
      "P"
    ], 
    "samvadi": "P", 
    "thaat": "Poorvi", 
    "time": "After sunset, 3-6", 
    "vadi": "r"
  }, 
  "Shuddha Barari": {
    "aaroha": [
      "S", 
      "r", 
      "G", 
      "P", 
      "D", 
      "N", 
      "S'"
    ], 
    "avaroha": [
      "S'", 
      "N", 
      "D", 
      "P", 
      "G", 
      "r", 
      "S"
    ], 
    "jati": "Shadav-Shadav", 
    "pakad": [
      "G", 
      "P", 
      "D", 
      "N", 
      "D", 
      "P", 
      "P", 
      "G", 
      "r"
    ], 
    "samvadi": "S", 
    "thaat": "Marva", 
    "time": "Evening, 6-9", 
    "vadi": "P"
  }, 
  "Shuddha Kalyaan": {
    "aaroha": [
      "S", 
      "R", 
      "G", 
      "P", 
      "D", 
      "S'"
    ], 
    "avaroha": [
      "S", 
      "N", 
      "D", 
      "P", 
      "P", 
      "M", 
      "G", 
      "R", 
      "S"
    ], 
    "jati": "Audav-Sampurna", 
    "pakad": [
      "S", 
      "'D", 
      "'P", 
      "'D", 
      "S", 
      "R", 
      "G", 
      "P", 
      "G", 
      "P", 
      "R", 
      "S"
    ], 
    "samvadi": "D", 
    "thaat": "Kalyaan", 
    "time": "Evening, 6-9", 
    "vadi": "G"
  }, 
  "Shuddha Sarang": {
    "aaroha": [
      "N", 
      "S", 
      "R", 
      "M", 
      "P", 
      "N", 
      "S'"
    ], 
    "avaroha": [
      "S'", 
      "N", 
      "D", 
      "P", 
      "M", 
      "P", 
      "m", 
      "R", 
      "N", 
      "S'"
    ], 
    "jati": "Audav-Shadav", 
    "pakad": [
      "R", 
      "M", 
      "P", 
      "R", 
      "m", 
      "R", 
      "S'", 
      "N", 
      "'P", 
      "'N", 
      "'D", 
      "S", 
      "'N", 
      "R", 
      "S"
    ], 
    "samvadi": "P", 
    "thaat": "Kafi", 
    "time": "Early Afternoon, 12-3", 
    "vadi": "R"
  }, 
  "Shuklabilaval": {
    "aaroha": [
      "S", 
      "G", 
      "m", 
      "P", 
      "G", 
      "m", 
      "P", 
      "D", 
      "N", 
      "S'"
    ], 
    "avaroha": [
      "S'", 
      "n", 
      "D", 
      "P", 
      "D", 
      "M", 
      "G", 
      "R", 
      "S"
    ], 
    "jati": "Shadav-Sampoorna", 
    "pakad": [
      "m", 
      "P", 
      "D", 
      "n", 
      "G", 
      "m", 
      "G", 
      "R", 
      "S"
    ], 
    "samvadi": "S", 
    "thaat": "Khamaj", 
    "time": "Morning, 6-9", 
    "vadi": "m"
  }, 
  "Shyam Kalyaan": {
    "aaroha": [
      "S", 
      "R", 
      "m", 
      "P", 
      "N", 
      "S'"
    ], 
    "avaroha": [
      "S'", 
      "N", 
      "D", 
      "P", 
      "M", 
      "P", 
      "G", 
      "m", 
      "R", 
      "S"
    ], 
    "jati": "Audav-Sampurna", 
    "pakad": [
      "R", 
      "P", 
      "G", 
      "m", 
      "R", 
      "'N", 
      "S"
    ], 
    "samvadi": "P", 
    "thaat": "Kalyaan", 
    "time": "Evening, 6-9", 
    "vadi": "R"
  }, 
  "Sindhura Chhaya": {
    "aaroha": [
      "S", 
      "R", 
      "m", 
      "P", 
      "D", 
      "m", 
      "P", 
      "N", 
      "S'"
    ], 
    "avaroha": [
      "S'", 
      "R'", 
      "n", 
      "D", 
      "P", 
      "m", 
      "G", 
      "m", 
      "P", 
      "g", 
      "R", 
      "S"
    ], 
    "jati": "Audav-Sampurna", 
    "pakad": [
      "m", 
      "P", 
      "D", 
      "m", 
      "P", 
      "N", 
      "S'", 
      "R'", 
      "n", 
      "D", 
      "P", 
      "m", 
      "G", 
      "m", 
      "P", 
      "g", 
      "R", 
      "S"
    ], 
    "samvadi": "S", 
    "thaat": "Kafi", 
    "time": "Early Morning, 3-6", 
    "vadi": "P"
  }, 
  "Sindura": {
    "aaroha": [
      "S", 
      "R", 
      "m", 
      "P", 
      "D", 
      "S'"
    ], 
    "avaroha": [
      "S'", 
      "n", 
      "D", 
      "P", 
      "d", 
      "m", 
      "P", 
      "g", 
      "R", 
      "m", 
      "m", 
      "g", 
      "S", 
      "R", 
      "S"
    ], 
    "jati": "Audav-Sampurna", 
    "pakad": [
      "m", 
      "P", 
      "D", 
      "S'", 
      "n", 
      "d", 
      "P", 
      "D", 
      "m", 
      "P", 
      "D", 
      "S'"
    ], 
    "samvadi": "P", 
    "thaat": "Asavari", 
    "time": "Morning, 9-12", 
    "vadi": "S'"
  }, 
  "Sohni": {
    "aaroha": [
      "S", 
      "G", 
      "M", 
      "D", 
      "N", 
      "S'"
    ], 
    "avaroha": [
      "S'", 
      "N", 
      "D", 
      "M", 
      "D", 
      "G", 
      "M", 
      "G", 
      "r", 
      "S"
    ], 
    "jati": "Audav-Shadav", 
    "pakad": [
      "M", 
      "D", 
      "N", 
      "S", 
      "r'", 
      "S", 
      "S", 
      "N", 
      "D", 
      "M", 
      "D", 
      "G"
    ], 
    "samvadi": "G", 
    "thaat": "Marva", 
    "time": "Before Sunrise, 3-6", 
    "vadi": "D"
  }, 
  "Sourashtrabhairav": {
    "aaroha": [
      "S", 
      "'N", 
      "S", 
      "m", 
      "G", 
      "D", 
      "N", 
      "S"
    ], 
    "avaroha": [
      "S", 
      "d", 
      "d", 
      "P", 
      "G", 
      "m", 
      "P", 
      "G", 
      "M", 
      "r", 
      "S"
    ], 
    "jati": "Audav-Sampurna", 
    "pakad": [
      "m", 
      "D", 
      "N", 
      "S'", 
      "S'", 
      "N", 
      "d", 
      "m"
    ], 
    "samvadi": "S", 
    "thaat": "Bhairav", 
    "time": "Before Sunrise, 3-6", 
    "vadi": "m"
  }, 
  "Sugharayi": {
    "aaroha": [
      "S", 
      "R", 
      "g", 
      "m", 
      "P", 
      "n", 
      "P", 
      "S'"
    ], 
    "avaroha": [
      "S'", 
      "n", 
      "D", 
      "n", 
      "P", 
      "m", 
      "P", 
      "g", 
      "m", 
      "R", 
      "S"
    ], 
    "jati": "Shadav-Sampoorna", 
    "pakad": [
      "S", 
      "n", 
      "D", 
      "n", 
      "n", 
      "P", 
      "m", 
      "R", 
      "S", 
      "R", 
      "g"
    ], 
    "samvadi": "S", 
    "thaat": "Kafi", 
    "time": "Late Evening, 6-9", 
    "vadi": "P"
  }, 
  "Suha": {
    "aaroha": [
      "n", 
      "S", 
      "g", 
      "m", 
      "P", 
      "n", 
      "m", 
      "P", 
      "S'"
    ], 
    "avaroha": [
      "S'", 
      "n", 
      "P", 
      "m", 
      "P", 
      "g", 
      "m", 
      "R", 
      "S"
    ], 
    "jati": "Audav-Shadav", 
    "pakad": [
      "'n", 
      "S", 
      "g", 
      "g", 
      "m", 
      "P", 
      "g", 
      "m", 
      "R", 
      "S"
    ], 
    "samvadi": "S", 
    "thaat": "Kafi", 
    "time": "Late Evening , 6-9", 
    "vadi": "m"
  }, 
  "Tilak Kamod": {
    "aaroha": [
      "S", 
      "R", 
      "m", 
      "P", 
      "N", 
      "S'"
    ], 
    "avaroha": [
      "S'", 
      "P", 
      "n", 
      "D", 
      "P", 
      "D", 
      "m", 
      "G", 
      "S", 
      "R", 
      "G", 
      "R", 
      "S"
    ], 
    "jati": "Shadav-Sampoorna", 
    "pakad": [
      "'P", 
      "'N", 
      "S", 
      "R", 
      "G", 
      "S", 
      "R", 
      "P", 
      "m", 
      "G", 
      "R", 
      "S", 
      "P", 
      "D", 
      "m", 
      "P", 
      "S'", 
      "P"
    ], 
    "samvadi": "P", 
    "thaat": "Khamaj", 
    "time": "Late Evening, 6-9", 
    "vadi": "S"
  }, 
  "Tilang": {
    "aaroha": [
      "S", 
      "G", 
      "m", 
      "P", 
      "N", 
      "S'"
    ], 
    "avaroha": [
      "S'", 
      "n", 
      "P", 
      "m", 
      "P", 
      "G", 
      "m", 
      "P", 
      "m", 
      "G", 
      "S"
    ], 
    "jati": "Audav-Audav", 
    "pakad": [
      "m", 
      "P", 
      "N", 
      "S'", 
      "n", 
      "P", 
      "G", 
      "m", 
      "G", 
      "S"
    ], 
    "samvadi": "N", 
    "thaat": "Khamaj", 
    "time": "Late Evening, 6-9", 
    "vadi": "G"
  }, 
  "Todi abheri": {
    "aaroha": [
      "S", 
      "R", 
      "G", 
      "m", 
      "P", 
      "d", 
      "P", 
      "D", 
      "n", 
      "S'"
    ], 
    "avaroha": [
      "S'", 
      "n", 
      "d", 
      "P", 
      "m", 
      "g", 
      "r", 
      "S"
    ], 
    "jati": "Vakra", 
    "pakad": [
      "R", 
      "m", 
      "P", 
      "d", 
      "P", 
      "g", 
      "r", 
      "g", 
      "r", 
      "S", 
      "R", 
      "G", 
      "m", 
      "P", 
      "D", 
      "n", 
      "S'", 
      "R'", 
      "n", 
      "d", 
      "P", 
      "m", 
      "P", 
      "g", 
      "r", 
      "g", 
      "r", 
      "S"
    ], 
    "samvadi": "g", 
    "thaat": "Asavari", 
    "time": "Evening, 6-9", 
    "vadi": "d"
  }, 
  "Triveni": {
    "aaroha": [
      "S", 
      "r", 
      "r", 
      "S", 
      "S", 
      "r", 
      "G", 
      "P", 
      "G", 
      "P", 
      "d", 
      "P", 
      "S'"
    ], 
    "avaroha": [
      "S'", 
      "N", 
      "d", 
      "P", 
      "P", 
      "G", 
      "r", 
      "r", 
      "S"
    ], 
    "jati": "Audav-Shadav", 
    "pakad": [
      "S", 
      "r", 
      "P", 
      "d", 
      "P", 
      "S'", 
      "N", 
      "d", 
      "P", 
      "G", 
      "P", 
      "G", 
      "r"
    ], 
    "samvadi": "P", 
    "thaat": "Poorvi", 
    "time": "Morning, 6-9", 
    "vadi": "S"
  }, 
  "Uttari gunakali": {
    "aaroha": [
      "S", 
      "r", 
      "g", 
      "m", 
      "m", 
      "P", 
      "d", 
      "n", 
      "S'"
    ], 
    "avaroha": [
      "S'", 
      "n", 
      "d", 
      "P", 
      "d", 
      "m", 
      "P", 
      "g", 
      "g", 
      "m", 
      "r", 
      "S"
    ], 
    "jati": "Sampurna-Sampurna", 
    "pakad": [
      "d", 
      "m", 
      "P", 
      "d", 
      "m", 
      "P", 
      "g", 
      "g", 
      "m", 
      "r", 
      "S"
    ], 
    "samvadi": "P", 
    "thaat": "Bhairav", 
    "time": "Morning, 6-9", 
    "vadi": "S"
  }, 
  "Vasanth": {
    "aaroha": [
      "S", 
      "G", 
      "M", 
      "d", 
      "N", 
      "S'", 
      "m", 
      "G", 
      "M", 
      "d", 
      "N", 
      "S'"
    ], 
    "avaroha": [
      "S'", 
      "N", 
      "d", 
      "P", 
      "M", 
      "G", 
      "M", 
      "G", 
      "r", 
      "S"
    ], 
    "jati": "Audav-Sampurna", 
    "pakad": [
      "M", 
      "d", 
      "r'", 
      "S'", 
      "N", 
      "d", 
      "P", 
      "M", 
      "G", 
      "M", 
      "G"
    ], 
    "samvadi": "P", 
    "thaat": "Poorvi", 
    "time": "Early Morning, 3-6", 
    "vadi": "S'"
  }, 
  "Vasanthmukhari": {
    "aaroha": [
      "S", 
      "r", 
      "G", 
      "m", 
      "P", 
      "d", 
      "n", 
      "S'"
    ], 
    "avaroha": [
      "S'", 
      "N", 
      "D", 
      "P", 
      "m", 
      "G", 
      "R", 
      "S"
    ], 
    "jati": "Sampurna-Sampurna", 
    "pakad": [
      "P", 
      "d", 
      "n", 
      "d", 
      "P", 
      "G", 
      "m", 
      "R", 
      "S"
    ], 
    "samvadi": "S", 
    "thaat": "Bhairav", 
    "time": "Morning, 6-9", 
    "vadi": "P"
  }, 
  "Vibhas": {
    "aaroha": [
      "S", 
      "r", 
      "G", 
      "P", 
      "d", 
      "S'"
    ], 
    "avaroha": [
      "S'", 
      "d", 
      "P", 
      "G", 
      "r", 
      "S"
    ], 
    "jati": "Audav-Audav", 
    "pakad": [
      "G", 
      "P", 
      "d", 
      "G", 
      "P", 
      "G", 
      "r", 
      "S"
    ], 
    "samvadi": "r", 
    "thaat": "Bhairav", 
    "time": "Morning, 6-9", 
    "vadi": "d"
  }, 
  "Vihang": {
    "aaroha": [
      "N", 
      "r", 
      "G", 
      "M", 
      "D", 
      "N", 
      "S'"
    ], 
    "avaroha": [
      "r'", 
      "N", 
      "D", 
      "P", 
      "M", 
      "G", 
      "r", 
      "G", 
      "m", 
      "G", 
      "r", 
      "S"
    ], 
    "jati": "Sampurna-Sampurna", 
    "pakad": [
      "G", 
      "m", 
      "r", 
      "G", 
      "m", 
      "G", 
      "G", 
      "M", 
      "D", 
      "M", 
      "G", 
      "G", 
      "r", 
      "S"
    ], 
    "samvadi": "N", 
    "thaat": "Poorvi", 
    "time": "Night, 6-9", 
    "vadi": "G"
  }, 
  "Yaman (Kalyaan)": {
    "aaroha": [
      "N", 
      "r", 
      "G", 
      "M", 
      "D", 
      "N", 
      "S'"
    ], 
    "avaroha": [
      "S'", 
      "N", 
      "D", 
      "P", 
      "M", 
      "G", 
      "m", 
      "G", 
      "R", 
      "S"
    ], 
    "jati": "Shadav-Sampoorna", 
    "pakad": [
      "'N", 
      "R", 
      "G", 
      "M", 
      "P", 
      "R", 
      "G", 
      "m", 
      "G", 
      "R", 
      "G", 
      "R", 
      "'N", 
      "R", 
      "S"
    ], 
    "samvadi": "N", 
    "thaat": "Kalyaan", 
    "time": "Evening, 6-9", 
    "vadi": "G"
  }, 
  "YamaniBilaval": {
    "aaroha": [
      "S", 
      "R", 
      "G", 
      "P", 
      "D", 
      "N", 
      "S'"
    ], 
    "avaroha": [
      "S'", 
      "N", 
      "D", 
      "P", 
      "D", 
      "n", 
      "D", 
      "P", 
      "M", 
      "G", 
      "m", 
      "G", 
      "R", 
      "G", 
      "R", 
      "S"
    ], 
    "jati": "Shadav-Sampoorna", 
    "pakad": [
      "D", 
      "n", 
      "D", 
      "P", 
      "M", 
      "G", 
      "m", 
      "G", 
      "R"
    ], 
    "samvadi": "D", 
    "thaat": "Kalyaan", 
    "time": "Morning, 6-9", 
    "vadi": "G"
  }
}
